{
    "book_id": "చందమామ_1948_09",
    "stories": [
        {
            "title": "దొందు - దొందు",
            "page_start": 7,
            "author": "ఏ టు కూరి",
            "pdf_page": 8,
            "content": "ఇంగిలీసు మాస్టరు గా రొకమా\nరెక్ట్ఫా క్లాసుకు వచ్చాడు\nతెలుగు టెక్ట్సునటునిటు ద్రిప్పుచునొక\nతిప్పకాయ ని ట్లడిగాడు.\n\nపంతులు:\n‘మనుచరిత్ర వ్రాసిన దెవరబ్బాయ్?’\n\nఅబ్బాయి:\n‘మర్లిసాని వ్రాసాడండీ:’\n\nపంతులు:\n‘సిట్‌దా నేడ్చా’ వంటుండగనే\nఅబ్బాయి:\n‘శ్రీనాథుడు వ్రాసా’ డనియెన్.\n\nపంతులు కా దని వండ్లు గొఱుకగా\nబాలుడు పకపక లాడాడు.\nమాస్టరు కుర్కోశము రాగా హె\nడ్వాస్టరు తెక్కులు చెప్పాడు.\n\nహెడ్మాస్టరు రసిస్టెంటుతో\nఈలా సంభాషించాడు:\n\n‘పిల్ల వెధవ మాటల కేమందోయ్?\nతల్లిక్రిందుగా చెప్తారు.\nఆ టైటలు పేజీపై వావి\nళ్ళండు సన్సు వా రని ఉంటే\n“శ్రీనాథుడు మలసా”నని చెపటం\nచిత్రంగానే ఉందండీ?\nఏటికినవుతా’ రంటూ క్లాసుకు\nనోటీసును బంపించాడు.\nశాస్త్రులు ‘దొందూ\nదొంద’ని నవ్వుచు\nసంతకమును బె\nట్టంపాడు.\n\nరచన: ‘ఏటు కూరి’\n\nపాఠాభషకం\n\nమహాత్మని చావు\n\nకొత్తరినముల్లు\n\nహైదరాబాదు"
        },
        {
            "title": "ధర్మసందేహము",
            "page_start": 10,
            "author": "జే. రామచంద్రన్",
            "pdf_page": 11,
            "content": "పూర్వం ఒక గ్రామంలో ఒక గురువు ఇద్దరు శిఘ్యులు వుండేవారు. ఒకసారి గురువుగారు తన శిఘ్యులతో సహా అప్రక్క గ్రామానికి బయలుదేరారు.\n\nకొంతదూరం వచ్చేసరికి గురువుగారికి దాహంవేసింది. ఆ చుట్టుప్రక్కల చూస్తే ఎక్కడా నీటి చుక్క కనిపించలేదు. కాని, ఆ దగ్గర్లోనే ఒక చిన్నవూరు కనిపించింది. గురువుగారు తనశిఘ్యులలో ఒకణ్ణి పిలిచి, “శిష్యా చాలాదాహంగా వుంది. కాస్త దాహం తీర్చుకునిగాని బయలుదేర లేను. నువ్వు ఆ కనపడే పూళ్లోకిపోయి ఎవరినైనా అడిగి కాసిని చల్ల చుక్క పట్టుకురా.నువ్వువచ్చేదాకామేము ఈచెట్టు క్రింద విశాంతి తీసుకుంటాం” అన్నారు.\n\nశిఘ్యుడు సరేనని బయలుదేరి ఆ పూళ్లో ఒక ధనవంతుని ఇంటికిపెళ్లి తమ గురువు గారు దాహంకోరినసంగతి చెప్పి కాసిని చల్ల యివ్వమని అడిగాడు. ఇంటి యజమాని ‘సరే ఆలాగే యిస్తాను వుండండి.’\n\nఅని లోపలికి పొయాడు.\n\nఇంతలో శిఘ్యుడికళ్లు అక్కడే వున్న పశువులకొట్టంపై పడ్డాయి. కొట్టంలో ఒక గేదెకు బారెడేసి కొమ్ములు వునైన్నె. అప్పుడు శిఘ్యుడికి ఒక ధర్మసందేహం కలిగింది.\n\n“ ఆరెరే, ఈ గేదెకి ఇంతపాడుగుకొమ్ములున్నయ్యే! ఒకవేళ యిది చస్తే దీన్ని ఇంట్లోంచి బయటికిలాగటమెలాగా?” అని.\n\nశిఘ్యుడు యిలా ఆలోచిస్తుండగా ఇంటి యజమాని చల్ల తీసుకొచ్చాడు. ఆయన్ని చూడగానే శిఘ్యుడు చల్ల తీసుకోకుండానే, “ఏమండీ! మీ గేదెకి యింత బారాటికొమ్ములున్నయ్యే! ఒకవేళ ఇది చస్తే దీన్ని బయటికి ఎలాఈడుస్తారండి?” అని అడిగాడు.\n\nఇది వినేసరికి ఇంటియజమానికి చాల కోపం వచ్చింది. “చాలు చాల్లేవయ్యు. చల్లకని వచ్చినవాడివి నీపని నువ్వు”\n\nచూసుకుపోక నా గేదె చస్తుందని అశుభం\nపలుకుతావా ? నీకు చల్ల యివ్వను ఫో”\nఅని వెనక్కి తిరిగిచూడకుండా యింట్లోకి\nపొయాడు.\n\nశిఘ్యడు తెల్లమొహం వేసుకొని వట్టి\nచేతుల్తో గురువుగారి దగ్గిరికి తిరిగొచ్చి,\nజరిగినదంతా చెప్పకుండా, “ఈ వూళ్లో\nఎవరూ చల్ల యివ్వ 0 అన్నారు” అని\nచెప్పాడు. అప్పడు గురువుగారు తన రెండో\nశిఘ్యణ్ణి పిలిచి, “ఒరే నువ్వన్నాపోయి\nసాధించుకురారా. దాహం మరీ ఎక్కువవు\nతోంది” అన్నారు.\n\nరెండోశిఘ్యుడు కూడా బయలుదేరి అదే\nయింటికివచ్చి చల్ల అడిగాడు.\n\nఅప్పడు యింటియజమాని, అంతకు\nముందే ఒకతనువచ్చి చల్లఅడిగినసంగతి,\nతర్వాత తన గేదె చస్తుందేమోనని అశుభం\nపలికిన సంగతి చెప్పాడు. అంతా విని,\nచివరికి ఈ శిఘ్యుడు “వాడిమొహం, వాడికేం\nతెలుసు! గేదె చస్తేనేం? దానికొమ్ములు\nరెండూ సరికి పారేస్తే తేలికగా బయటికి\nలాగెయ్యవచ్చు” అన్నాడు తన బుర్రలో\nవున్న తెలివినంతా ఉపయోగించి.\n\nఇది వినేసరికి యింటియజమానికి అరి\nకాలి మంట నెత్తికెక్కింది. “ఏమయ్యా,\nనుప్యూ ఘనుడివేనే! ఏమో అనుకున్నాను.\nమొదటవచ్చిన అతను గేదె చస్తుందేమో\nఅనిమాత్రం తనేసి పూరుకున్నాడు. నువ్వు\n\nగేదె చావటం, కొమ్ములుకోసి పారెయ్యటం\nకూడా అనేశావా? పో, పో, నీకు చల్ల\nయివ్వను ” అన్నాడు. శిఘ్యుడు చేసేదిలేక\nపట్టిచేతుల్తో గురువుగారి దగ్గిరికి వచ్చాడు.\n\nఅప్పుడు గురువుగారు తనమూడోశిఘ్యణ్ణి\nపిలిచి “ఇక నువ్వన్నా నిర్వాకం చేసు\nకురా. నీ వల్ల కాకపోతే అప్పుడు యిక\nనేనే పోతాను” అని పంపాడు.\n\nమూడోశిఘ్యుడు కూడా అదే యింటికి\nవచ్చి చల్ల అడిగాడు. అప్పుడు యింటి\nయజమాని అంతకుముందు యిద్దరు వచ్చి\nయిలాగే చల్ల అడిగి, మొదటి అతను\nఅశుభం పలికిన సంగతి, రెండో అతను\nఅంతకంటే అశుభంగా మాట్లాడినసంగతి\n\nచెప్పాడు. అంతా విని, శిఘ్యుడు, “వాళ్ళ మొహం, వాళ్ళకి ఆ మాత్రం తెలివితేటలు వుంటే యింకేం! గేదె చస్తేనేం? దాని తల వరకూ నరికివేస్తే, తలవేరే మొండెం వేరే బయటికి తేలికగా చేర్చవచ్చు” అన్నాడు.\n\nఇది వినేసరికి యింటియజమానికి ఒళ్లు మండిపోయింది. “ఇక కట్టిపెట్టవయ్యా. ఇంకా ఏదో చెప్పాచ్చా వనుకున్నాను. నీ కంటె వాళ్లేనయమనిపించారు. నడు, నడు. వచ్చినదారినే పో. నీకు చల్ల యివ్వను” అన్నాడు.\n\nఈ శిఘ్యుడుకూడా వట్టి చేతుల్లో తిరి గెచ్చే సరికి గురువుగారికి చాల చిన్నతన మైంది. వాళ్ళ అపయోజకత్వం తనకే తలవంపులని అనుకున్నాడు. “అయినా కాస్త చల్లచుక్క ఇవ్వడానికి ఎవరికీ దయ కలగకపోవడానికి కారణ మేమై ఉంటుందా?” అని ఆలోచిస్తూ - “సరే, ఏంజేస్తాను? నేనేపోయి ముష్టితుతాను. నేను వచ్చేవరకూ యిక్కడ వుండండి” అని ముగ్గురు శిఘ్యల్నీ చెట్టుకింద వదిలి పెట్టి గురువు కూడా బయలుదేరి అదే ఇంటికి వచ్చాడు.\n\nఇంటియజమాని గురువుగారితో అంతకు ముందు వచ్చిన ముగ్గురి సంగతీ, వాళ్ళు ఒక్కొక్కరు ఎలా అశుభం పలికిందీ చెప్పాడు. అంతా విని, గురువుగారు ఇలా అన్నారు: “వాళ్లతెలివి తెల్లారినట్టే ఉంది. ఈపాటి స్వల్పవిషయానికి పెద్ద ఆలోచన కావాలా. గేదె చచ్చిందే అనుకోండి. ఆ చచ్చినచోటనే ఒక పెద్ద గె య్య తీ నీ దాంట్లో గేదెనిపూడ్చి పెట్టవచ్చునుగదా!”\n\nఇది వింటుంటే యింటి యజమానికి గురువుగారిని ఆవళాన సమిలిమింగేద్దామా అన్నంత కోపంవచ్చింది. ఆమూల నున్న దుడ్డుకర్ర తీసుకొని “చాలు చాల్లేవయ్యా, ఇక అట్టే వాగావంటే నీప్రాణం దక్కదు. నీ కంటె ఆ ముగ్గురే నయమనిపించారే. పో, ఇంకా మజ్జిగఅడగవచ్చావా సిగ్గులేక” అంటూ గురువు వెంబడి పడ్డాడు. గురువు వెనక్కితిరిగి చూడకుండా కాలికి బుద్ది చెప్పి శిఘ్యులదగ్గిరికి చేరుకున్నాడు.\n\nఇక ఒక్క కీణం కూడా అక్కడవుంటే తమ ప్రాణాలు దక్కవని, నాలుక పిడచ కట్టుకు పోతున్నా, గురువు శిఘ్యులతోసహా అక్కడినించి మకాం ఎత్తేశాడు."
        },
        {
            "title": "బంగారు పక్షి",
            "page_start": 13,
            "author": "ఆర్. వెంకటేశ్వర్లు",
            "pdf_page": 14,
            "content": "పూర్వం పాటలీపుత్రాన్ని విక్రమసింహ డనే రాజు పాలించేవాడు. ఆతడు ప్రజలను దయతో చూడటంపల్ల ప్రజలకు అతనంటే ఎంతో గౌరవం ఉండేది. ఆతనికి ముగ్గురు కొడుకు లున్నారు. ఒక కూతురు కూడా ఉంది. పెద్ద కొమారుని పేరు శూర సేనుడు. రెండవవాని పేరు భారవేలుడు. మూడవవాని పేరు విజయా పాలుడు. కూతురు పేరు మందారవతి.\n\nరాజు ప్రతిరోజు రథముమీద షికారుకు వెళ్లేవాడు. తోటలో నుండి వచ్చేటప్పుడు ఒక మామిడిచెట్టుకు ఒకబంగారపు కాయ చూసేవాడు. మరుసటిరోజున ఉదయం ఎవరైనా బ్రాహ్మణుడికి ఇవ్వాలని అనుకొని ఇంటికి వెళ్లిపాయ్యేవాడు. రెండవరోజున వచ్చిచూస్తే కాయ కనపడేదికాదు. ఇలా కొద్దికాలం జరిగింది. రాజు ఒకరోజున శూర సేనుని విలిచి మామిడికాయ ఎవరు తీసి కొని పోతున్నదీ కనిపెట్టమని చెప్పాడు. సరే అని పెద్దకొడుకు సాయంత్రం భోజనంచేసి\n\nవెళ్ళాడు. రాత్రి పదకొండు గంటలవరకు ఓపికతో కూర్చున్నాడు. కాని నిద్రవచ్చి పండుకొన్నాడు. ప్రాద్దున్న చూస్తే కాయ కనబడలేదు. రెండవ రాత్రి భారవేలుడు కాపలాకాశాడు. ఇతడుకూడా రాత్రి పం డ్రెండు గంటలకు నిద్రపోయాడు. ఆ రాత్రి కూడా కాయ ఎవరు తీసికొని పోయింది తెలియలేదు. మూడవరాత్రి విజయాపాలుడు కాపలా కాశాడు. రాత్రి ఒంటిగంటకు ఒక బంగారపురంగు పడివచ్చి కాయను ముక్కుతో తుంచి ఎగిరిపోతున్నది. విజయాపాలుడు బాణంతో ఆపకీని కొట్టాడు. పడి ఎగిరిపోయింది కాని, బాణము ఆ పడి రెక్కకు తగిలి ఒక ఈక క్రిందపడింది. ఆ ఈక బంగారురంగు కలిగి చాలా అందంగా ఉంది. దానిని తీసికొనివెళ్ళి తండ్రికి యిచ్చాడు. విక్రమసింహుడు ఆ ఈకనుచూచి చాల అశ్చర్యపోయాడు. పడిని తీసికొనివచ్చినవారికి తన రాజ్యంలో సగం భాగం యిస్తానన్నాడు.\n\nశూరసేనుడు సరే అని బయలు\nదేరివెళ్లి నక్క చెప్పిన మేడలదగ్గరకు\nవచ్చాడు. దీపములతో ఉన్న మేడ\nచూశాడు. లోపల సృత్యవాద్యములు\nజరుగుతున్నాయి. రెండవ వైపు\nమేడను చూస్తే చీకటిగా ఉంది. ఈ\nచీకటి మేడలోకి వెళ్లి నేనేం చెయ్యను\nఅనుకొని దీపములున్న మేడలోకి వెళ్ళాడు.\nలోపలకు వెళ్ళగానే వారకాంతలు అత\nనికి సారాయి తాగించి ఆటపాటలలోకి\nదింపార్షు, శూరసేనుడు ఇక యిల్లుమా టే\nమరచిపోయాడు.\n\nశూరసేనుడు పటిని తీసుకొనిరావటానికి\nబయలుదేరాడు. దారిలో ఒక నక్క\nకనబడి, “ఎక్కడికి పొతున్నావు\nయువరాజా” అని అడిగింది.\n\n“బంగారుపటికోసము వెళ్లుతున్నా”\nనని చెప్పాడు శూరసేనుడు.\n\nఆప్పుడు నక్క యిలాఅంది: “నీపు వెళ్లి\nటప్పుడు దారిలో రెండు మేడలుకనిపిస్తాయి.\nఒకమేడలో దీపాలు వెలుగుతూఁంటాయి.\nసృత్య వాద్యాలు జరుగుతుంటాయి. రెండవమేడ చీకటిగా ఉంటుంది. చీకటి\nమేడలోకి వెళ్లినట్లయితే పటి దొరుకుతుంది.\nదీపాలున్న మేడలోకి వెళ్లవద్దు.”\n\nచాలకాలంవరకు శూరసేనుడు రాక\nపోవడంపల్ల ఖారవేలుడు బయలుదేరాడు.\nఇతనికికూడ దారిలో నక్కశనబడి, యిది\nవరకు శూరసేనుడికి చెప్పినట్లే చెప్పింది.\nఇతడుకూడ సృత్యవాద్యాలు జరుగుతున్న\nమేడలోకి వెళ్ళాడు. మళ్లీ తిరిగి రాలేదు.\n\nఖారవేలుడుకూడ చాల కాలంపరకు\nరాకపోవడంపల్ల విజయపాలుడు పటికోసం\nబయలుదేరాడు. ఇతనికి కూడ నక్క\nదారిలో కనబడి చీకటి మేడలోకి వెళ్ళ\nమని చెప్పింది. సరే అనిచెప్పి మేడల\nదగ్గరకు వచ్చాడు. దీపములున్న మేడ\nలోకి తొంగిచూచాడు. చాలమంది ఆడ\nవాళ్లు కనబడ్డారు. సృత్యవాద్యాలు జరుగు\nతున్నాయి. “మారాజ్యంలో అనేక రకాల\n\nసృత్యాలు బరుగుతుండగా ఈ సృత్యాలే\nచూడాలా” అని అనుకొని చీకటి మేడ\nలోక వెళ్ళాడు. కాని లోపల ఏమీ కన\nబడలేదు. తిరిగి బయటికి వచ్చేటప్పటికి\nనక్క కనబడింది. “పకి కనబడుతుందని\nచెప్పాపుగదా? ఏది?” అని అడిగాడు.\nనక్క అతన్ని తన వీపుమీద కూర్చేమంది.\nవిజయపాలుడు అలాగే కూర్చున్నాడు.\nనక్క అతనిని ఒక కోటదగ్గరకు తీసికొని\nపోయి యిలాచెప్పింది: “నీవు కోటలో ఏడు\nగుమ్మములు దాటినతరువాత ఒక బంగారు\nపకి కనబడుతుంది. దారిలో నిన్ను\nఎవ్వరూ ఆడ్డగించరు. అక్కడ రెండు\nపంజరము లుంటాయి. ఒకటి బంగారు\nపంజరము. రెండవది కఱ్ఱ పంజరము.\nనీవు ఆ పకిని బంగారు పంజరములో\nపెట్టక కఱ్ఱ పంజరంలో ఉంచి తీసుకురా.”\n\nవిజయపాలుడు సరేనని కోటలో ప్రవే\nసించి ఏడు గుమ్మములు దాటగానే పకి\nకన్పించంది. పకి చాల అందంగా పుంది.\nప్రక్కనున్న పంజరముల రెంటిని\nచూచాడు. బంగారు పకిని కఱ్ఱ పంజ\nరములో ఉంచితే బాగుండదని బంగారు\nపంజరంలో ఉంచాడు. పకి వెంటనే\nకూసింది. తకణం రాజభటులుపచ్చిపట్టు\nకొని అతనిని రాజుదగ్గరకు తీసుకువెళ్ళారు.\n\n“నీవు ఎవరవు? ఎందుకు మా కోటలోకి వచ్చావు?” అని అడిగాడు రాజు.\n\n“మాది పాటలీపుత్రము. నేను విక్రమ\nసింహుని కొడుకును. మా తోటలోని\nమామిడికాయను ప్రతిరోజు ఈ పకి తీసికొని\nవస్తోంది. ఒక రోజు రాత్రి నేను దనిని\nచూచి బాణంతో కొట్టాను. కాని గురితప్పి\nరెక్క చివర తగిలి ఒక ఈక క్రింద\nపడింది. నేను దానిని మా తండ్రికి\nచూపించాను. దానిని చూడగానే మా\nతండ్రి ఈపకి కావాలన్నారు. అందుకని\nవచ్చాను” అన్నాడు విజయపాలుడు.\n\nరాజు తనకు ఒక “బంగారు గుఱ్ఱము”\nపట్టితెచ్చి ఇస్తే తాను బంగారు పకిని\nయిస్తా సన్నాడు. గుఱ్ఱాన్ని ఒక నెల\n\nచందమామ\n\nదినములలో తీసికొని రాకపోతే తనను\nవెదకి పట్టించి తల సరిక స్తాన న్నాడు.\nవిజయపాలుడు అలాగే గుణ్ణాన్ని తెచ్చి\nఇస్తానని చెప్పి బయటికి వచ్చాడు.\n\nమళ్లీ నక్క కనిపించి \"పకి యేమైంది\"\nఅని అడిగింది. విజయపాలుడు జరిగిం\nదంతా చెప్పాడు. నక్క అతడ్ని వీపుమీద\nకూర్చోబెట్టుకొని యింకొక కోట దగ్గరకు\nతీసికొని పచ్చింది. అక్కడ కూడ\nనక్క రాజకుమారునితో \"ఏడవగుమ్మము\nదాటిన తరువాత ఒకగుణ్ణం కసబడుతుంది.\nఅక్కడే ఒక బంగారుజీను, ఒక తోలుజీను\nవుంతై. గుణ్ణంమీద బంగారుజీను వెయ్యక\n\nతోలుజీను వేసుకొనిరా” అని చెప్పింది.\nసరేనని విజయపాలుడు కోటలో\nప్రవేశించి ఏడు గుమ్మములు దాటాడు.\nఆఖారి గుమ్మముదగ్గర గుణ్ణం కన్పించింది.\nప్రక్కనే రెండుజీనులు వునై. అంత\nఆందమైన గుణ్ణానికి తోలుజీను బాగుండదని\nబంగారుజీను వేశాడు. వెంటనే గుణ్ణం\nసకిలించింది. రాబభటులు వచ్చి అతనిని\nపట్టుకొని రాజుదగ్గరకు తీసికొని వెళ్ళారు.\n\nరాజు అతనిని “నీవవరపు? ఎందుకు\nమా కోటలోకి వచ్చావు?” అని అడిగాడు.\nవిజయపాలుడు జరిగినదంతా చెప్పాడు.\n\nరాజు తనకు \"బంగారురాణిని\" యిస్తే\nతాను బంగారు గుణ్ణాన్ని యిస్తానన్నాడు.\nపదిహేనురోజులలోగాని రాకపోతే తల\nనరికిస్తానన్నాడు.\n\nవిజయపాలుడుబయటకువచ్చాడు.మళ్లీ\nనక్కకన్పించి గుణ్ణం ఏమైందని అడిగింది.\nతాను చేసిన పారబాటును చెప్పాడు.\nనక్కకు చాలకోపంపచ్చింది. కాని అతనిని\nఏమీ అనలేదు. మళ్ళీ అతనిని తన\nవీపుమీద ఎక్కించుకొని యింకో కోట\nదగ్గరికితీసికొనివచ్చి \"కోటలోకివెళ్లినతర్వాత\nఒక తోట కనబడుతుంది. అందులో ఒక\nచెఱువు ఉంటుంది. అక్కడకు రాత్రి\nపండ్రెండు గంటలకు ఒక రాజకుమార్తె\nస్నానానికి వస్తుంది. నీవుచెట్టుచాటున దాగి\n\nచందమామ\n\nఆమెను పట్టుకుంటే నీతో కూడా పస్తానని అంటుంది. మళ్లీ నీపు వెనుకకు పంప కుండా ఆమెని తీసికొని రా” అని చెప్పింది.\n\nవిజయపాలుడు సరేనని లోపలకు వెళ్ళి తోటలో చెట్టుచాటున దాక్కున్నాడు. రాత్రి పండ్రెండు గంటలకు రాజకుమార్తె స్నానానికి వచ్చింది. విజయపాలుడు వెనగ్గా వెళ్లి ఆమెని పట్టుకున్నాడు. ఆప్ప డామె “నీతో వచ్చేస్తాను” అంది. అతడు సరే అని రాణిని తీసికొని పస్తున్నాడు. కొంత దూరం వచ్చిన తరువాత రాణి తన తల్లి దండ్రులను చూచివస్తాననిచెప్పింది. కాని అతడు వినిపించుకొనకుండా ముందుకు సాగిపొతున్నాడు. రాణి అతడ్నిబ్రతిమాలింది. కాని అతను ఒప్పుకోలేదు. ఆమె ఏడ్చింది. విజయపాలుడు “సరే వెళ్లి త్వరగారా” అన్నాడు. ఆమాట ఆనేలోపలనే రాజ భటులు వచ్చి అతనినిపట్టుకొని రాజుదగ్గ రకు తీసికొనివెళ్లారు.\n\nరాజు అతనిని “నీవెందుకు పచ్చావు?” అని ఆడిగాడు. విజయపాలుడు తాను వచ్చినపనిని చెప్పాడు. ఆప్పుడు రాజు కిటికీలో నుంచి ఒక పెద్దకొండను చూపించి దానిని వారం రోజులలో త్రవ్వి వేయమన్నాడు. అలాగ త్రవ్వినట్లయితే తన కూతుర్ని యిస్తానన్నాడు. లేకపొతే బుర్ర తీయిస్తానన్నాడు. ఒక పార, గున\n\nపము, తట్ట యిచ్చారు. అవి పట్టుకుని బయటకు వచ్చాడు విజయపాలుడు. మళ్లీ సక్క ఎదురైంది. రాణిని తీసుకొని రాసందుకు సక్కకు చాల కోపము వచ్చి అతనితో మాట్లాడకుండా వెళ్లిపోయింది.\n\nపాపం విజయపాలుడు అ కొండ దగ్గ రకు వెళ్లి అక్కడే ఏడుస్తూ కూర్చున్నాడు. ఐదు రోజులు గడచిపోయినాయి. కాని, కొండమాత్రం మామూలుగానే ఉంది.\n\nఆరవరోజుననక్కవచ్చి రాజకుమారుణ్ణి కొండ త్రవ్వలేదేమని ఆడిగింది. అతడు సమాధానం చెప్పలేదు. నక్క వెళ్లి పోయింది.\n\nచందమామ\n\nఏడవరోజు రాత్రి మళ్లీ నక్క ఆక్కడికి వచ్చి చూసింది. అతడు నిర్దపోతూనే ఉన్నాడు. తెల్లవారితే గడువు తిరిపోతుంది. రాజుగారు ఉరిటేస్తాడు. అప్పుడు నక్క కొండను మాయం చేసింది. ఉదయం రాజకుమారుడు లేచి చూచేటప్పటికి కొండ కనబడలేదు. కంగారుపడినక్క నుండిగాడు. నక్క తాను మాయం చేశానని చెప్పింది.\n\nఇంతలో రాజభటనలు విజయపాలుణ్ణి రాజుదగ్గరకు తీసుకువెళ్లారు. “కొండ త్రవ్వేవా?” అని అడిగాడు రాజు.\n\nవిజయపాలుడు “త్రవ్వా”నని చెప్పాడు. రాజు దూరదర్శిని యంత్రంతో చూచాడు.\n\nకొండ లేదు. దానికి ఆపత్రలఁపిన్న గ్రామా లన్నీ కనపడ్డాయి. అప్పుడు రాజు తన కుమార్తెను విజయపాలుని కచ్చి పంపాడు.\n\nఆద్దరూ నక్కమీద కూర్చుని బంగారు గుఱ్ఱంఉన్న కోటదగ్గరకుపచ్చారు. రాబినీ, గుణ్ణాన్నికూడ విజయపాలునికే వచ్చేటట్లు చేయాలని నక్క అనుకుంది. రాజ కుమారునితో నక్క “నీవు రాబినిలోపలకు తీసికొని వెళ్లినతరువాత రాజు నీకు గుణ్ణాన్ని యిస్తాడు. దాని ముఖం కోటవైపు ఉంచే టట్లు చూచి రాబితో వెళ్లిపోతానని చెప్పు. అప్పుడు రాబినీ నీకు నమస్కారం చేస్తుంది. వెంటనే రాబిని గుఱ్ఱంపైకి లాగి చల్ అనగానే గుఱ్ఱం పరుగెత్తుకొని వచ్చే స్తుంది” అని చెప్పింది. సరే అని రాజ కుమారుడు రాబిని కోట లోపలకు తీసికొని వెళ్లాడు. రాజు గుణ్ణాన్ని తీసుకొచ్చి విజయ పాలునికి ఇచ్చాడు. విజయపాలుడు గుఱ్ఱం మీద కూర్చుని రాబితో వెళ్లి పోతానని చెప్పాడు. రాబిని నమస్కరించింది. అప్పుడు రాబిని పైకి లాగి గుణ్ణాన్ని 'చల్' అని అన్నాడు. వెంటనే గుఱ్ఱం పారిపోయింది. నక్క గుఱ్ఱంవెనుక పరుగెత్తింది. రాజు కొందరు రొతులను పంపించాడు. కాని గుఱ్ఱం దొరకలేదు.\n\nవిజయపాలుడు తిన్నగా పడి ఉన్న కోటదగ్గరకు వచ్చాడు. నక్క పడిని,\n\nచందమామ\n\nగుజ్జాన్ని కూడా రాజుకుమారునికి వచ్చే\nటట్లు చేద్దామనుకొంది. అతనితో “నీవు\nగుజ్జాన్ని లోపలకు తీసికొని వెళ్లిన తరువాత\nపకీని పంజరములో పెట్టి నీకిస్తారు. వెను\nకటి వలెనే గుజ్జాన్ని చల్ అనగానే వచ్చే\nస్తుంది” అని చెప్పింది. విజయపాలుడు\nలోపలకు వెళ్లి పంజరాన్ని పట్టుకొని నక్క\nచెప్పినట్లు చల్ అన్నాడు. వెంటనే గుఱ్జం\nఅక్కడనుంచి పారిపోయింది. రాబి\nనక్కమీద కూర్చుంది. నక్క గుఱ్జం వెన\nకాల పరుగెడుతోంది.\n\nఆలా వాళ్లు తిన్నగా యిదిపరకు వచ్చిన మేడలదగ్గరకు వచ్చారు. ఆక్కడ\nఆగి విజయపాలుడు నక్కతో “నీవు నాకు\nచాల సహాయంచేశావు. నీకు ఏది కావాలో\nకోరుకో. ఇస్తాను” అన్నాడు.\n\n\"నీ చేతిలో ఉన్న బాణంతో సన్నుకొట్టు.\nఅంతకన్న వేరేసహాయం నాకు అక్కర్లెదు\"\nఅన్నది నక్క.\n\n\"అమ్మయ్యో! నాకు నీవు ఎన్నో కష్టాలు పడి ఈ మూడింటిని సంపాదించి ఇచ్చావు. నిన్నుమాత్రం నేను చంపలేను\" అన్నాడు విజయపాలుడు.\n\nనక్క పోనీలే అని చెప్పి \"నీవు వెళ్లేటప్పుడు దారిలో యిద్దరను ఉరి తీస్తూ ఉంటారు. వారిని మాత్రము కొనవద్దు. కాని, ఒకవేళ కొన్నా నూతి ఆంచుమీద\n\nమాత్రం కూర్చోవద్దు” అని చెప్పింది. విజయ\nపాలుడు నరే అని చెప్పి బయలుదేరాడు.\n\nదారిలో ఒకచోట ఇద్దరు మనుష్యు\nలను ఉరితియ్యడం చూచాడు. దగ్గరకు\nవెళ్లాడు. వాళ్లు తన సోదరులే !! వారిని ఉరి\nతియ్యటానికి కారణం విమిటని అడిగాడు.\nవాళ్లు అప్పలుచేసి ఎంతకాలమైనా తీర్చక\nపోవడంవల్ల ఉరితీస్తున్నామని చెప్పారు.\nవిజయపాలుడు వాళ్ళకు రావలసిన డబ్బు\nయిచ్చి తన సోదరులను విడిపించాడు.\n\nముగ్గురుకలసి వెడుతున్నారు. దారిలో\nఒకచోట కూర్చున్నారు. ఏవేఏ మాటలు\nచెప్పి అతడ్ని సోదరులిద్దరు ఒక నూతి\n\nచందమామ\n\nదగ్గరకు తీసికొనిచ్చి మాతి అంచుమీద\nకూర్చోపెట్టారు. పాపం, నక్క చెప్పిన\nమాట విజయపాలుడికి జ్ఞాపకంలేదు.\nమాటల సందడిని శూరసేన, భారవేలు\nలిద్దరు అతనిని నూతిలోకి త్రోసివేసి,\nరాణీనీ, గుజ్జాన్నీ. పకీనీ తీసికొనిపాయి\nతండ్రికి చూపించారు. తామే తీసుకొని\nవచ్చామని చెప్పారు. అప్పటినుంచి రాణి\nఎవరితోనూ మాట్లాడటంలేదు. గుఱ్ఱం గడ్డి\nమేయటం లేదు. పకీ పలకటం లేదు.\n\nనక్క నూతిదగ్గరకు వచ్చి చూసింది.\nవిజయపాలుడు లోపల ఉన్నాడు. \"నేను\nనిన్ను నూతి అంచుమీద కూర్చోపద్దని\nచెప్పాను గదా! మరి యిలా ఎందుకు జరి\nగింది?\" అని నక్క అడిగింది. విజయ\nపాలుడు ఏమీ మాట్లాడలేదు.\n\n\"ఇప్పుడైనా నన్ను చంపుతావా ? నిన్ను\nజైటకు తీస్తాను\" అని అడిగింది నక్క.\n\n\"సరే అలాగే\" అన్నాడు. నక్క నూతి\nలోకి దూకి తనతోక గట్టిగా పట్టుకోమంది.\nవిజయపాలుడు అలాగే చేశాడు. నక్కపైకి\nఒక్ష గంతువేసింది. ఇద్దరూ బయటపడ్డారు.\n\nతర్వాత విజయపాలుడు బాణంతో\nనక్కను కొట్టాడు. వెంటనే నక్క ఒక\n\nచక్కని రాజకుమారునిగా మారిపోయింది.\nవిజయపాలుడు ఆశ్చర్యపోయి, \"నీ వెవ\nరవు? ఎందుకీ నక్కరూపంతో ఉన్నావు?\"\nఅని అడిగాడు.\n\n\" నేను ఒక మునిశాపంపల్ల నక్కగా\nమారిపోయాను. బంగారురాణి నా చెల్లెలు\"\nఅని చెప్పాడు. ఇద్దరూ కలసి పాటలీపుతం\nబయలుదేరారు.\n\nవిజయపాలుడు పట్టణంలో అడుగు\nపెట్టగానే ఆ కణంపరకు ఏమీ తినకుండా\nదిగులుగా వుంటున్న రాణీ, గుఱ్ఱం, పకీ\nఎంతో సంతోషంగా కన్పించసాగినై. రాణి\nతల దువ్వుకొని క్రొత్తబట్టలు కట్టుకొంది.\nగుఱ్ఱం త్వరగా గడ్డిమేయసాగింది. పకీ\nమాట్లాడటం ప్రారంభించింది. విరిద్దరు\nయింటికి వచ్చి విక్రమసింహునితో జరిగిన\nదంతా చెప్పారు. అప్పుడు విక్రమసింహుడు\nరాణిని పిలిచి, అడిగాడు! రాణికూడ\nనిజం చెప్పింది. శూరసేనుణ్ణి, భార\nవేలుడ్ని పిలిపించి ఉరిశిక్షవిధించాడు.\nవిజయపాలుడికి బంగారు రాణిని, తన\nకూతురైన మందారవతిని రాణిసోదరునకూ\nయిచ్చి గొప్ప వైభవంతో పెండ్లి చేశాడు.\n\nకథ కంచికెళ్లింది, మనమింటికిపచ్చాం.\n\nస్వామ్యాలు, అమ్మాయిలూ!\n\nప్రే చిక్కుచ్చడరంలో ఒకమూల కోడి, మరో మాం దాని విల్లాదాపునై కోడి ఆహా రానికి ఐయలుదేరి దాలదూరం వచ్చేవింది. తిరిగి యింటి తెలాటోవాలో తెలియక ఆలో చిత్తోంది. మీకు దారితెలిస్తే, పాపం, కోడిని దాని విల్లాదగ్గరికి చేర్చండి చూడ్డాం.\n\nనాగుపాము ముగ్గులు\n\nఈ ముగ్గులు పంపినది: దీ, విజయలక్ష్మి, మద్దాసు."
        },
        {
            "title": "వర్ధమానుని విదేశ యాత్రలు",
            "page_start": 22,
            "author": "చందమామ బృందం",
            "pdf_page": 23,
            "content": "( గతనంచిక తరువాయి )\n\nఅది జరిగిన కొద్దికాలానికే వర్ధమానుడు\nరాజధాని నగరానికి పోవటానికి అనుమతి,\nఆహ్వానమూ కూడా సంపాదించాడు.\n“మనిషిపర్వతం” వస్తున్నవార్తవినగానే\nజనమంతా ఇళ్లలో దూరారు. అనేకమంది\nఅతన్ని చూడటానికి ఇళ్ళకప్పులెక్కారు.\nరాజవీధుల్లో తప్ప అతనికి నడవటానికి\nజాగాలేదు. ఊరిమధ్య రాజభవనంఉంది.\nదానిచుట్టూ ప్రహరీగోడ లున్నాయి.\nవర్ధమానుడు వాటిమీదిగా అంగవేసి\nఅంతపుర ఆవరణ ప్రవేశించాడు. అతను\nలోపల ఉన్న ఆసనాలూ, తివాసీలూ మొద\nలైనవి చూడటానికి నేల బారుగా పడుకుని\nకిటికిలో నుంచి చూడవలసి వచ్చింది.\n\nరాజుగారు చూపిన ఆదరానికి వర్ధమానుడు చాలా సంతోషించాడు. తన కృతజ్ఞత యెట్లా చూపడమా అని ఆలోచించాడు. ఇందుకు అవకాశం త్వరలోనే కలిగింది.\n\nవామనద్వీపానికి దగ్గిరలో మరొక చిన్న ద్వీపం ఉన్నది. అక్కడి ప్రజలు కూడా వామనులవంటివారే. వారిపేరు గుజ్జులు. గుజ్జులకూ వామనులకూ అనాదిగా పోట్లాట లున్నాయి. కాని ఇటీవల కొద్దిమాసాలుగా ఈ పోట్లాటలకు విరామం కలిగింది. కారణ మేమంటే గుజ్జులరాజు వామనుల మీద దాడిచెయ్యటానికి కొన్ని కొత్తనావలు సిద్ధం చేయించాడు. ఈ యుద్ధనావలు\n\nయిప్పుడు సిద్ధమయాయనీ, గుజ్జులు ఏ కీణాన అయినా దండెత్తి రావచ్చుననీ వామనరాజుక్క కబురు వచ్చింది. అయన పర్ధమానుడి సహాయం కోరాడు. వామను లకు సహాయంచేస్తాననీ, తాను చెప్పినట్టు చేస్తే గుజ్జుల యుద్ధనౌక లన్నిటినీ పట్టి తెస్తాననీ వర్ధమానుడు చెప్పాడు.\n\nరాజుకు పరమానందం కలిగింది. ఏమేమి కావాలో చెప్పి చేయించుకోమన్నాడు. వర్ధమానుడు తనకు తగినంత మోకూ, లావుపాటి ఇనపచువ్వలూ\n\nకావాలన్నాడు. కాని వామనుల దగ్గిర ఉన్న మోకులు ట్వయిను దారంకంపె ఆపే లావులేవు; ఇనపచువ్వలు తీగె మేకుల లాగున్నాయి.\n\nవీటితోనే వర్ధమానుడు పని ప్రారంభించాడు. తనకుడిరిసిన తాటిని మూడుపెటల పేని కాస్తబలమైన తాడు తయారుచేశాడు. ఈ విధంగా యాభైతాళ్లు తయారుచేశాడు. మూడేసిచువ్వలు కలిపి మెలిపెట్టి, వంచి, యాభైకొంకలు తయారుచేశాడు. ఒక్కొక్క తాటి చివరా ఒక్కొక్క కొంక కట్టాడు."
        },
        {
            "title": "నక్కసాయం",
            "page_start": 29,
            "author": "గోకరాజు బంగారమ్మ",
            "pdf_page": 30,
            "content": "అనగనగా ఒక ఊళ్లో ఒక బీద బ్రాహ్మడు ఉండేవాడు. ఆయన ప్రతి రోజు ప్రక్కనున్న పట్టబానికి యాయవార మెత్తుకోసానికి పొతూఉండేవాడు. రోజు పొద్దున్నే వెడుతూ ఉండేటప్పుడు దారిలో మన బాపనయ్యకు ఒక నక్క కనిపిస్తూఉండేది. బాపనయ్య ఆ నక్కను కూర్చోబెట్టి \"యీవేళ మంగళవారం, దశమి తిథి, శతభిష నక్షత్రం, పగలువర్ణయంలేదు” అని పంచాంగం తీసి నక్కకి చెప్పి మరిపోతూఉండేవాడు.\n\n“ఓ పిచ్చిబ్రాహ్మడా ! నాకు పంచాంగ మెందుకు ? నేను నీ కేమన్నా యిచ్చే దాన్నా ? చేసేదాన్నా ? అయినా నా రాచ కార్యాలన్నీ చెడిపోతున్నాయి కనకనా ?” అని అంటూ వింటూవుండేది నక్క.\n\n“ నక్కబావా ! నక్కబావా ! నువ్వు నాకేమి యివ్వ నక్కరలేదు. నీ దయ నా మీద ఉంటే చాలు” అని వెళ్లిపోతూ ఉండే వాడు బాపనయ్య.\n\nఈలా రోజు నక్కకి పంచాంగము చెప్పనిదే వేళ్లేవాడుకాదు. బ్రాహ్మణ్ణి చూచి నప్పు డల్లా 'యీయన కేమి సాయం చేయ లెక పోతున్నామే' అని బాధపడుతూ ఉండేది నక్క. ఈలాగ చాలా రోజులు గడిచిపోయాయి.\n\nఅపట్టబాన్ని అశక్తభూపాలుడనే మహా రాజు పాలిస్తూ ఉండేవాడు. ఆయన ఒక సామంతరాజును మోసపుచ్చి, అతని కూతుర్ని ముసలితనంలో మూడో పెళ్ళిచేసుకున్నాడు. ఆ ముసలిరాజుతో కాపురం చెయ్యడాని కిష్టంలేదు, ఆ ముద్దుల రాణికి. అందుచేత రాజుగారికి తెలిము కుండా తన ఆభరణాలూ, కట్టుకొనే బట్టలూ ఆన్నీ తీసుకొని ఒకనాటి అర్ధరాత్రి వేళే తన కన్నవారింటినించి వచ్చిన చాకలి సాయంతో రాణి పుట్టింటికి బయలుదేరింది.\n\nపట్టణందాటి వచ్చేశా రిద్దరూ. ఊరు బయట పారుతోందో ఉప్పుటేరు. అర్ధరాత్రి అవడంచేత అక్కడ నావలేమీ లేవు. “ముందుగా నగలూ, బట్టలూ అన్నీ అవత లొడ్డుకు చేర్చి తరువాత మిమ్మ ల్ని చేరుస్తాను” అన్నాడు చాకలి. రాణీ కూడా సరేనంది. చాకలికి బట్టలూ, ముక్కుపుడకతో సహా ఆభరణాలూ అన్నీ యిచ్చింది రాణీ. అవన్నీ తీసుకొని సురకీతంగా ఏటి అవతలి ఒడ్డుకి చేరు కున్నాడు చాకలి. ఇంక ఆలోచన మొదలెట్టాడు. “రాణీని నేను కన్నవారింటికి తీసు కెళ్లినట్లు తెలిస్తే రాజు నన్ను చంపుతాడు.\n\nఈవిణ్ణి తీసుకువెళ్లడమంటే బుద్ధిపూర్వ కంగా చావు కోరుకోవడమన్న మాట.” ఇలా అనుకుని ఆభరణాలతోటి పరా రయ్యాడు చాకలి. ఇవతలొడ్డునుంచి కేకలువేయ మొదలెట్టింది రాణి. జవాబు చెప్పడానికి వాడక్కడుంటేగా? చాకలి యెంతసేపటికీ రాకపోవడం, తను ఒక్కరై ఒంటరిగా ఉండడం, ఇంతలో తెల్లవార బోతూఉండడం, యీవన్నీ రాణికి పిచ్చెత్తి నట్లయి ఆలోచిస్తూ కూర్చుంది.\n\nఇంతలో హో మాంసపు ముక్కు నోట కరచుకొని ఆ దారే పొతోంది మన నక్క. తిన్నగా రాణీఉన్న రేవుదగ్గర కొచ్చేసరికి ఏటిలో ఓ చేప ఎగరడం చూసిందినక్క. వెంటనే తన నోట్లోఉన్న మాంసపుముక్కు ఒడ్డున పారేసి, ఏట్లో వున్న చేపకొసరం ఉరికింది. నక్క ఉరికేసరికి ఏట్లో చేప కాస్తాదాటి పొయిండి. ఒడ్డున ఉన్న మాంసపు ముక్కు ఒక డేగ తన్నుకు పొయింది. నక్క యిటు చేపకూ, ఆటు ముక్కకూ రెంటికీ చెడి తెల్లబో యి నుంచుంది ఒడ్డున.\n\nనక్కస్థితి అంతాచూచి ఫక్కున సవ్వింది, మనపడుచు రాణి. సవ్వడమే కాకుండా పరిహాసం కూడా ఆడింది. దాంతో నక్కకు ఎక్కడలేని కోపం వచ్చింది. “ఓసిపిచ్చిదానా! ముందు నీగతి\n\nచూచుకో. ఇటు పుట్టింటికి చెడ్డావు. అటు\nమెట్టినింటికి చెడ్డావు. నాకేం. కాస్సేపు పాలా\nల్లోకి వెళ్లానంటే అన్నీ మాంసపుముక్కలే,\nఅని సమాధాన మిచ్చింది నక్క.\n\nనక్క సమాధానం వినేసరికి రాబీకి\nమరీ ఖంగా రెత్తింతి. “నా కథ నీ కెట్లా\nతెలుసు?” అని నక్క నడిగింది.\n\n\"నీ కధే కాదు. నీ అటు మూడుతరాలు,\nఇటు మూడుతరాలు ఏకరువు పెడతాను.\nకావలిస్తే విను” అంది నక్క. ఇకరాణికి\nమతిలేక నక్కని బ్రతి మాలుకోవడం\nమొదలెట్టింది, తనకీ గండం తప్పించమని.\n\nనక్క కాసే పాలోచించి, \"నాకోసాయం\nచేయాలి. ఆది చేస్తా నంటే చెప్తా\"నంది.\n\n“ఓ దానికేం, నాకీ గండం తప్పించా\nవంటే నీకు వంటినిండా ముత్యాలు,\nరత్నాలు కురిపించేస్తాను” అన్నది రాణి.\n\nఅప్పుడు ఉపాయశాలిమైన ఆ నక్క\nయీ విధంగా అలోచనచెప్పింది: “నువ్వు\nఏట్లోదిగి కూర్చుని జుట్టు ముడివిప్పి విర\nటోసుకో. పిచ్చపిచ్చగా కేకలువేస్తూ ఉండు.\nనీ కేకలుచిని పట్టణంలో వాళ్ళంతా యిక్క\nడికి చేరుతారు. నీ హడావిడి చూసి నీకు\nపిచ్చెత్తిందనీ, ఏట్లోపడి కొట్టుకుంటూ కేకలు\nపెడుతున్నావనీ పుకార పుట్టిస్తారు. ఈసంగతి\nరాజు చెవిని కూడ పడుతుంది. అప్పుడు\n\nఆయన నిస్సు తీసికెళ్ళి నీకు అనేక\nవైద్యాలుచేయిస్తాడు. ఎంతమంది వెద్యులు\nచచ్చినా నీపుమాత్రం రెచ్చిపొతూనేఁండు.\nనేను శుక్రవారం ప్రాద్దున్నే వే బ్రాహ్మణ్ణి\nవంపుతాను. ఆయన వచ్చి నీ చెవిలో\n'నక్క పంపిన బ్రాహ్మణ్ణి' అని ఊదు\nతాడు. అంతటితే నీ విచ్చ తగ్గిపోయినట్టు\nనటించు. ఇదే నీపు నాకు చెయ్యవలసిన\nసాయం. ఈ సాయం, యిప్పుడు చేస్తానని\nచెప్పి తర్వాత అలా చెయ్యకపోతే నిన్ను\nఈ ఒక్క పట్టణమే కాదు. ఎక్కడా\nతలెత్తుకు తిరగటానికి లేకుండా చేస్తాను\n\nజాగ్రత్త! తెలిసిందా?” అని చెప్పి వెళ్లి\nపొయింది నక్క. సరేనని రాణి జుట్టు\nవిరబోసుకొని ఆ ఏటిలో కొట్టుకుంటూ\nపిచ్చి కేకలు మొదలెట్టింది.\n\nతెల్లవారేసరికి ఈ వార్త ఆనోటా ఆనోటా\nపాకి కోటకు చేరింది, రాజుగారి భార్యకి\nపిచ్చెత్తిందనీ. ఏట్లోపడి కొట్టుకుంటోందనీ.\nరాజుగారి కిదితెలిసి తన భార్యకి నిజంగా\nపిచ్చెత్తిందనుకొని పదిమంది దాసీల\nనిచ్చి మేనా పంపాడు. ఆ దాసీలు పచ్చి\nరాణీకి బట్టలుకట్టి మేనా లో యొక్కించి\nయింటికి చేర్చి గదిలో పెట్టి తాళంవేశారు.\n\nగదిలో ఉండి మేడంతా దద్దరిల్లేటట్లు\nఅల్లరిచేస్తోంది రాణి. వేళకి తిండితినదు.\nపిచ్చకేకలు. ఇవన్నీ రాజుకు మరింత\nఖంగా రెత్తించాయి. ఎంతోమంది వైద్యులు\nపస్తున్నారు, చూస్తున్నారు. కాని ఏంలాభం\nవైద్యులని చూచినకొద్ది రెచ్చిపోయి\nవాళ్ళని కొట్టడం తెట్టడం కూడా చేస్తోంది.\nఇది చూచి వైద్యంచెయ్యడానికి కూడా\nఎవరూ రావడంలేదు. ఈలా నాలుగు\nరోజులు గడిచాయి. రాణీ పిచ్చతోపాటు\nరాజుకు బెంగకూడా ఎక్కువైంది.\n\nఆ నాడు శుక్రవారం. మామూలుగానే\nనక్కబావకు పంచాంగము చెప్పాడు\nబ్రాహ్ముడు. నక్క రాణీతో చెప్పిన\nరోజు ఆదే, “ఓ బ్రాహ్ముడా! నేను నీ కేమి\nయివ్వకపొయినా, నీ విధి నీవు నెరవేరు\nస్తున్నావు. మన పట్టణం రాణీకి పిచ్చె\nత్తింది. నీవు వెళ్లి ఆ పిచ్చ బాగుచెయ్యి.\nనీకు కావలనినంత ధనం యిస్తాడు రాజు\nగారు. దాంతో నీ దరిద్రం తీరిపోతుంది”\nఅని చెప్పింది సక్క.\n\nఆ మాట వినగానే ఆ పరికిబాప డౌక్క\nసారి ఉలిక్కిపడి “నాకేం మంత్రాలొచ్చా,\nతంత్రాలొచ్చా, పైగా ఆ పిచ్చది విలెంప\nకాయన్నా కొట్టిందంటే నా పెళ్ళాం బిడ్డ\nలకు నేను దూరమైపోతాను. నా తెందుకు!\n\nనాదారిన నన్ను పొని వ్వు” అన్నాడు\nబ్రాహ్మడు.\n\n“సికు మంత్రాలేమీ రా సక్కర్లెదు.\nరాణీదగ్గర కెళ్ళి ఆవిడ చెవిలో ‘నక్క\nపంపిన బ్రాహ్మణ్ణ’ అని చెప్పు. దాంతో\nపచ్చి ఎగిరిపోతుంది” అని చెప్పింది నక్క.\nనక్క మాటప్రకారం కోట గుమ్మం\nదగ్గరి కెళ్ళాడు బ్రాహ్మడు. లోపలి కెళ్ళ\nడానికి బంటోతులు ఆటకాయించారు.\n“నేను వైద్యం చేస్తాను. రాణీగారి పిచ్చ\nనేను కుదర్చకపోతే నన్ను మారు పేరెట్టి\nపిలవండి” అని డబాయించి మరీ వెళ్లాడు\nలోపలికి. తిన్నగా రాజుగారి దర్శనంచేని\nవైద్యంచేయడానికి అనుమతి ఇవ్వవలసిన\nదని కోరాడు. ఏ పుట్టలో ఏ పాముందో\nఆనుకొని రాజు ఒప్పుకున్నాడు.\n\nమన బాపనయ్య రాణీఁ ఉన్న గది దగ్గర\nకెళ్లి చూసి కావలసిన ఏర్పాటు లన్నీ\nచేయించుకొన్నాడు. రాణీ తన మీదబడి\nకొట్టకుండా ముందుగా గౌలుసువేయించి\nకట్టించేశాడు బ్రాహ్మడు. తనకి మంత్రా\nలొచ్చినట్టు నటించి హ్రాం, హ్రాం, హ్రోం\nఆని ఏవేవో కొన్ని మంత్రాలు చదివి,\nఎవళ్లూ లేకుండగా చూచి, గదితలుపులు\nదగ్గరగావేసి, రాణీ దగ్గర కెళ్ళి మెల్లగా\nచెవిలో “నేను సక్క పంపిన బ్రాహ్మణ్ణి\nనుమా” అని ఊదేశాడు.\n\nవెంటనే రాణీ తన ఎచ్చకేకలూ, పచ్చ\nపనులూ అన్నీ మానుకొంది. ఈసంగతి విన్న\nరాజుగారు ఎంతో ఆచ్చర్యపోయారు.\n\nఆమర్నాడు పెద్దసభ ఏర్పాటుచేయించి,\nఎంతోమంది వైద్యులు కుదర్చలేకపోయిన\nపిచ్చను బ్రాహ్మడు కుదిర్చినందుకు రాజు\nగారు ఆతన్ని ఎంతో గౌరవించి. ఎన్నో\nముత్యాలూ, రత్నాలూ, కెంపులూ,\nభూములు యిచ్చి సత్కరించాడు. నాటితో\nమన బ్రాహ్మడి దరిద్రం రెక్కలు వచ్చిన\nపిట్టలాగు ఎగిరిపోయింది.\n\nచూశారా, చెల్లాయిలూ! నక్క బ్రాహ్మడి\nకెంత సాయంచేసిందో !\n\nచందమామ"
        },
        {
            "title": "అజ్ఞాన శిరోమణి",
            "page_start": 34,
            "author": "నరహరిశెట్టి వెంకటరావు",
            "pdf_page": 35,
            "content": null
        },
        {
            "title": "అవ్యక్త మహారాజు",
            "page_start": 34,
            "author": "నరహరిశెట్టి వెంకటరావు",
            "pdf_page": 35,
            "content": "అజ్ఞానశిరోమణి\n\nఒకనాడు అజ్ఞానశిరోమణి దున్నపోతు\nలను కాస్తూఉండగా కొంచెం దూరంలో\nపున్న గేదెల మందలోనుంచి లేగదూడ\nఒకటి తప్పిపోయి పోతులమందలో కలి\nసింది. కొంతసేపటికి అజ్ఞానశిరోమణి\nయీ లేగదూడను చూచి “జౌరా, కాల\nమహిమ! దున్నపోతు ఈనిండి” అని అను\nకొని ఈ వింతసంగతి రాజుగారికి నివే\nదించాలనుకున్నాడు.\n\nతిన్నగా దున్నపోతును. లేగదూతతో\nసహా తోలుకొని రాజుగారి ఎదటికి వచ్చి,\n\"ప్రభూ! మనమందలో దున్నపోతు ఈ\nలేగదూడని ఈనింది\" అని మనవి చేసు\nకున్నాడు.\n\nరాజుగారు ఎంతో ఆశ్చర్యపడి మంత్రి\nవంకచూచి, \"మంత్రి! చాలా విచిత్రంగా\nఉంది\" అన్నారు.\n\nమంత్రికూడా \"చిత్తం, చిత్తం, మహా\nరాజా! గత యుగాలలో ఏ మహరాజు\nపరిపాలనలో కూడా ఇలాంటిది జరగ\nలేదండి\" అన్నాడు.\n\nరాజుగారు ఈ వింతపశువులను కొంత\nసేపు కన్నుల కరువుదీరునట్లుగా చూచి\nదున్నపోతును దూడను కట్టివేయమన్నారు.\n\nఅనగా అనగా ఒక ఊళ్లో ఒక రాజు\nవుండేవాడు. ఆయన పేరు అమాయకుడు,\nఎవరైనా ఓ మంచోచెడ్డో చెప్పితే శాంతంగా\nవినేవాడు. ముఖ్యంగా చాడికోరుమాటలు\nచెప్పేవారికే అగ్రతాంబూలం.\n\nఆయన మంత్రిపేరేమిటో తెలుసా?\nమాయకుడు, రాజూ మంత్రికూడా సార్థక\nనాములే. మంత్రి ఒక్కొక్కప్పుడు రాజు\nగారినే పల్టీకొట్టించి పట్టం కట్టుకునేవాడు.\nపైకి చాలా మంచివాడులాగా వుండేవాడు.\n\nరాజుగారి పశువుల కావర్లలో అజ్ఞాన\nశిరోమణి అని ప్రత్యేకం దున్నపోతులను\nకాసేవాడు ఒకడు వున్నాడు.\n\n# అవ్యక్తమహారాజు\n\nపిమ్మట రాజుగారు ఈవింతవిషయాన్ని ప్రత్యక్షంగా నిరూపించిన అబ్జానశిరోమణికి మంత్రిసలహాపైన ఒక జాగీరుయిచ్చి గార వించారు.\n\n* కొన్నిరోజులు గడిచినై. ఒకనాటిరాత్రి కోటలో రాజు, మంత్రి కూర్చుని ఆమాటా, ఈమాటా మాట్లాడుకుంటున్నారు. ఆవి చికటి రాత్రుళ్ళు. కోటకు ఒక ప్రక్క ఓ చిన్న ఏరు పారుతూ ఉంది. ఆ ఏటిఒడ్డున నక్కలు గుంపులు గుంపులుగా చేరి అర వడం మొదలు పెట్టాయి. ఖులాసాగా మాట్లాడుతున్న రాజుగారికి కోపం వచ్చి “ఏమోయ్, మంత్రి! ఆ నక్కలు ఎందుక లా అరుస్తున్నాయి?” అని ఆడిగాడు.\n\n“మహారాజా! ఇది శీతాకాలం. చలి ఎక్కువగా వుంది. చలిబాధకు తాళలేక ఆవి అలా ఆ రుస్తున్నాయి” అన్నాడు మంత్రి.\n\n“అవును పాపం, వాటికి కప్పుకోటానికి మనకుమల్లే దుప్పట్లులేవుగా!” అన్నాడు రాజు జాలిగా.\n\n“చిత్తం, మహాప్రభూ! నోరులేనివాటికి దుప్పట్లు ఎవరు కొనియిస్తారు” అన్నాడు మంత్రి.\n\n“ఒకరు కొనిచ్చేదేమిటి? మనమే యిద్దాం. రేపు మన ఖాజానాలోంచి రెండు వేల రూపాయలు తీసి దుప్పట్లు కొని ఒక్కొక్క నక్కకు ఒక్కొక్కటి చౌప్పన యిప్పించు” అన్నాడు రాజు.\n\nమంత్రి సరేసన్నాడు.\n\nతెల్లవారింది. మంత్రి ఖాజానాలో నుంచి అంత డబ్బూ తీసి చక్కగా తన యించికి పట్టుకువెళ్లి తాళం వేనుకున్నాడు.\n\nఆ రాత్రి మళ్లీ మామూలుగానే రాజు మంత్రి కోటలో కూర్చున్నారు. నక్కలు మళ్లీ అరవటం మొదలు పెట్టాయి. ఇది చినేసరికి రాజుకి ఆశ్చర్యం కలిగింది.\n\n“మంత్రి!దుప్పట్లుకొని పంచిపెట్టించావా?”\nఅని అడిగాడు.\n\n“చిత్తం. దేవర ఆజ్ఞప్రకారం అన్నిటికి తలొక దుప్పటి యిప్పించాను” అన్నాడు మంత్రి.\n\n“అల్లా తే మళ్లీ యీ నక్కలు అరుస్తు న్నయ్యి ఎందుకు?” అన్నాడు రాజు.\n\n“ప్రభువులు పారబడుతున్నారు. తమరు దయచేయించిన దుప్పట్లు కప్పుకొని, ఆవి తమకు కృతజ్ఞతచూపుతూ తమ కిర్తిని యిలా గానం చేస్తున్నాయి” అ న్నాడు మంత్రి.\n\n• నిజమేగదా అని సంతోషించాడా వెర్రి మహారాజు.\n\nమంత్రికి క్రమంగా దురాశప్పటింది. రాజ్యమంతా తానే కాజేయాలనుకున్నాడు.\n\nఒకనాడు మంత్రి రాజు తో యిలా అన్నాడు: “మహారాజా! శత్రురాజులు మన పైకి యుద్ధానికి వచ్చే సూచనలు కనపడుతున్నాయి. మనకు సైనికబలం తక్కువగా వుంది.”\n\n“మరైతే ఎదైనా మంచి ఉపాయం ఆలోచించు” అన్నాడు రాజు.\n\n“నేను ముందే ఆలోచించాను. పూర్వం ఆర్జునుడు పరమెశ్వరినిగూర్చి తపస్సుచేసి పాపుపతాస్తము సంపాదించాడు. దేవర వారు కూడా అడవికెళ్లి తపస్సు చేసి అలాంటిఅస్త్రం ఒకటి సంపాదించినట్లయితే శత్రుసంహారం సులువుగా చేయవచ్చును. ఈ లోగా నేను కోట లో నుంచి ఎప్పటి కప్పడు మీకు వార్తలు తెలియవరుస్తూ ఉంటాను” అన్నాడు మంత్రి.\n\nఈ మాటలు విని ఆ వెర్రి మా రాజు తపస్సు చెయ్యటానికి అడవికి వెళ్లాడు. ఆక్కడ పాపం ఆయన్ని క్రూరమృగాలు చంపివేశాయి.\n\nమంత్రి, రాజు చచ్చిపోయాడని తెలుసు కుని రాజ్యానికి తానే పట్టంకట్టుకున్నాడు. అజ్ఞానశిరోమణికి ఇదివరకు ఇచ్చిన జాగీరు తిరిగి లాగివేశాడు.\n\nమరికొన్ని రోజులు గడిచిన తర్వాత శత్రురాజులు నిజంగానే యుద్ధానికి వచ్చి మంత్రిని ఓడించి ఆ రాజ్యం కాస్తా ఆశ్రమించుకున్నారు.\n\nచూశారా ! వాడి అన్యాయం వాడినే కొట్టింది."
        },
        {
            "title": "మొండి నమ్మకం",
            "page_start": 37,
            "author": "యమ్. సత్యనారాయణరావు",
            "pdf_page": 38,
            "content": "మొందినమ్మకం\n\nఅనగా, అనగా ఒక పూర్ఛ కందుల\nసుబ్బడు అనే దీదవా డొక డుండేవాడు.\nఇతడు రోజు దగ్గరలో పున్న అడవికిపోయి,\nకట్టెలు కొట్టుకొని, ఊళ్ళో అమ్ముకుంటూ\nజీవనం చేస్తుండేవాడు. సాపం! అతని\nదరిద్రానికి తగ్గట్టుగా, గంపెడు మంది\nపిల్లలుకూడా పుట్టారు. ఇంతమంది పిల్లల\nతోనూ, భార్యతోనూ ఎల్లాగో ఒక గుడిసెలో\nకాపురం చేస్తున్నాడు.\n\nఇల్లా కొన్ని సంవత్సరాలు గడచి\nపోయాయి. మామూలుగా వాడొక రోజు\nఅడవికిపోయి కట్టెలు కొట్టుకుంటున్నాడు.\nకొట్టగా, కొట్టగా, ఆ చెట్టులో ఒక తొట్ట\nబైట పడింది. అందులో కొన్ని చీమలు\nకనిపించినై. వాటిముక్కులను నూకలు.\nఇది చూసిపాపం! సుబ్బడు విస్తుపోయి\nఇలా అనుకున్నాడు.\n\n“అరే! ఈ కారు అడవిలో ఈ చెట్టు తొట్టగలోనున్న చీమలకు ఆహార మిచ్చిన దేవుడు, నా కెందు కివ్వడు? ఈ రోజు ముదలుకొని నేనూ ఇంట్లో కూర్చుంటాను. ఈ చీమలకు ఆహారమిచ్చిన దేముడు, నాకూ, నా భార్యా పిల్లలకు మాత్రం ఆహారం ఎందుకివ్వడోచూస్తాను” అని అనుకుంటూ యింటికి పోయి కాళ్లు ముడుచుకుని పడుకున్నాడు. ఇంట్లో డబ్బు లేదు. భార్యగోల పెట్టింది “డబ్బులేదండి” అంటూ.\n\n“డబ్బు! చీమలదేముడు తెస్తాడు”\nఅంటూ కూర్చున్నాడు కందుల సుబ్బడు.\n\nఇదంతాచూచి, భార్య కేమీ తోచక,\nపిల్లల్ని పెంచటానికి, రోజు అడవికి వెళ్లి,\nఎర్రమన్ను త్రవ్వి అమ్ముకుంటూ కాల\nకేపం చేస్తున్నది. ఇలా, కొన్నాళ్లు గడచి\nపోయింది.\n\nసుబ్బడి భార్య, మామూలుగా ఒక\nరోజున అడవికి వెళ్లి, ఎర్రమన్ను త్రవ్వ\nతుండగా, ఏదో 'అ'క్కుమని తగిలింది.\nఏమా ? ఆని త్రవ్వి చూసేటప్పటికి, ఒక\nవిందె, బిందెనిండా కాసులు కనపడినై.\nఅవన్నీ-నెత్తినపెట్టుకు పొదామని మొదట్లో\n\nఆనుకుంది. కాని, కాస్సే పాలో చించి\n“అమ్మయ్యో! పట్టపగలు ఎవరు చూస్తే\nవిమోనమ్మా! నమ్మరాదు” అనుకుంటూ\nఆ కాసులు ఒక పెద్ద తట్టలోపోసి, పైన\nమూరడెత్తున ముళ్లుపెట్టి, గండు చీమలు,\nతేళ్ళు అందులో పడేసి ఇంటికి వెళ్లింది.\n\nక్రమంగా ప్రాద్దుకూకి చీకటపడడిది.\nరాత్రి పదిగంటలైంది. అప్పుడు సుబ్బడి\nభార్య, భర్తదగ్గిరికి వెళ్లి “విమండ!”\nఅడవిలో నాకోక కాసులబిందె దెరికింది.\nఆ కాసులన్నీ ఆ క్కడౌక తట్టలో\nపెట్టాచ్చాసు. తీసుకొద్దాం పదంది. మన\nదరిదం తీరుతుంది” అన్నది.\n\nచెప్పిందంతా విని సుబ్బడు “చీమల\nదేముడే తెస్తాడు” ఆని బండలా కూర్చు\nన్నాడు. భార్య ఎంతప్రతిమాలినా కదల్లేదు.\n\nఈ సంభాషణ ప్రక్కయింటికి కన్నం వేద్దామని వచ్చిన దొంగలు విన్నారు. విని, వినడంతో పదండిరా, ” అని చంకలు కొట్టుకుంటూ ఆ మనిషిచెప్పినచేటికి వెళ్లి తట్టలో చెయ్యి పెట్టేటప్పటికి, చిమలూ, తేళ్లూ తెగకుట్టి వదిలి పెట్టినై.\n\nఅప్పుడు \"అబ్బా! ఈ మాయలమారి మనల్ని మోసంచేసిందిరా; దీని రోగం కుదురుద్దా”మని ఆతట్ట తీసికెళ్లి ఆ గుడిసె పైన పెద్ద బొక్క పెట్టి దాంటో కుమ్మరించి పారిపోయారు. ముందు చిమలూ, ముళ్లూ, తేళ్లూ పడ్డయ్, ఆతరువాత గలగల మంటూ కాసులన్నీ పడ్డయ్. ఇదిచూసి సుబ్బడూ, సుబ్బడి భార్య ఆశ్చర్యపోయారు.\n\n\"చూశావా! నేను చెప్పలేదా చిమల దేముడే తెస్తాడని \" అంటూ సుబ్బడు లేచి గంతులు వెయ్యటం మొదలెట్టాడు. ఆ\n\nతమవాత, సుబ్బడు ఆడబ్బుతోనూ, భార్యా బిడ్డలతోనూ హాయిగా పూలరంగడులా కాలం వెళ్ళబుచ్చ సాగాడు.\n\nమీరుమాత్రం చిమల దేముడే తెస్తాడని కూచోకండేం! ఆకలయితే ఆన్నం పెట్టమని మీ అష్టు నడగండి."
        },
        {
            "title": "దొంగసన్యాసి",
            "page_start": 40,
            "author": "బి. వేణుగోపాల్",
            "pdf_page": 41,
            "content": "దొంగసన్యాసి\n\n(గతనంచిక తరువాయి)\n\nమ్యూడో ఏడు పూర్తిఅయిన మర్నాడు సన్యాసి మళ్లీ రాజు ఎద ట ప్రత్యక్ష మయ్యాడు. ఆన్నమాటను నెరవేర్చమని రాజును అడిగాడు.\n\nఆప్పుడు రాజుకి \"ముగ్గురిలో ఎవరెవ రిని యివ్వటమా?\" అని సందేహం కలిగింది. రాణీని సలహా అడిగాడు.\n\n\"మన తర్వాత మన పెద్దకుమారుడే కదా వారసుడు! అందుకని వాడిని యివ్వటానికి వీల్లెదు. మన పెద్దవాడికికూడా మనశాగే సంతానం కలగకపొతే, ఆప్పుడు మన రెండోవాడేగదా వారసుడు. కనక వాడినికూడా యివ్వటానికి వీల్లెదు. అందువల్ల ఎటొచ్చీ మనం యిచ్చుకో గలిగిందల్లా అఖిరివాడినే. అలాగే గుఱ్జప్పిల్ల కుక్కపిల్లల విషయంలోకూడా చేద్దాం.\" అని సలహా చెప్పింది రాణీ.\n\nసరేనని రాజు తన మూడో కుమారుణ్ణి, మూడోగుఱ్జప్పిల్లనీ, కుక్కపిల్లనీ సన్యాసికి సమర్పించి సాగనంపాడు.\n\nముందు సన్యాసి, అతని వెనకనే గుఱ్జం మీద రాజకుమారుడు, గుఱ్జం వెనకనే కుక్క బయలుదేరారు. వాళ్లు అలా పోయిపోయి చివరికి ఒక ఎత్తైన కొండ మీదికి చేరుకున్నారు. కొండ దిగువన ఒక లోయా, ఆ లోయలో ఒక కోటా వున్నయ్. సన్యాసి ఆ కోటను చూపుతూ రాజకుమారుడితో అన్నాడు — \"ఆ కని పించేదే నా యిల్లు. నేను నిన్ను యిప్పుడు ఈ కొండమీదనే వదిలి వెడతాను. నువ్వు నా యింటికి చేరుకోవాలి. నా యింటి బైటి వాకిలిదగ్గిర ఒక మేక కట్టివేసి ఉంటుంది. ఆ దగ్గర్లోనే ఒక గడ్డిమోపు వుంటుంది. నువ్వు ఆ గడ్డిమోపును మేక\n\nది. వేషుగోపాల్ — మద్రాసు\n\nముందు వెయ్యాలి. ఇది మొదటి పని.\nఈ పని చేసిగాని సువ్వు యింటి ఆవర\nణలో అడుగు పెట్టగూడదు.\n\n\"ఈపని చేసి సువ్వు యింటి ఆవరణం\nలోకి వెడితే ఆక్కడ నీకు కొన్ని కోళ్ళు\nకనిపిస్తుచి. ఆ దగ్గర్లోనే కొంత ధాన్యం\nపుంటుంది. సువ్వు ఆ ధాన్యం కోళ్ళు\nముందు చల్లాలి. ఇది రెండో పని.\n\n\"ఈ రెండుపనులూచేసి, నేను తిరిగి\nపచ్చేపరకూ నాయింట్లో ప్రవేశించకుండా\nబైటి ఆవరణలోనే కనిపెట్టుకు వుండాలి.\nఅలా గాకుండా యింట్లో ప్రవేసించబోయా\nపంటే సువ్వూ, నీ గుఱ్జం, నీ కుక్కా\nముగ్గురూ ఒక్కసారిగా చస్తారు\" అని\nచెప్పి సన్యాసి కొండదిగి త్వరత్వరగా వెళ్లి\nపోయాడు.\n\nపాపం, రాజకుమారుడికి ఏంచెయ్యాలో\nతోచలేదు. ఏదారినపోతే సన్యాసి యింటికి\nచేరుకోగలడే తెలియలేదు. కాని, దేవుడి\nమీద ఖారంచీసి బయలుదేరాడు. దారిలో\nఎన్నో గుట్టలు, మిట్టలు, వాగులు దాట\nవలసి వచ్చింది. చాల కప్పాలుపడి\nఅన్ని దాటాడు.\n\nఆలాగే మరి కొంతదూరం వచ్చేసరికి\nరాజకుమారుడి దారికి ఒక వెడల్పాటి\n\nకాలప అడ్డువచ్చింది. కాలవకి ఆవతలి\nవైపు కొంతదూరంలో కోట కనిపించింది.\nకోట కనిపించేసరికి రాజకుమారుడికి\nమనస్సు స్థిమిత పడింది. కాని కాలప\nదాటటం ఎట్లా? కొంత సేపు ఆలోచించాక\nరాజకుమారుడికి ఒక ఉపాయం తట్టింది.\nతను గుఱ్జంమీద ఎక్కాడు. కుక్కని\nఒళ్లో కూర్చోపెట్టుకుని గుణ్ణాన్ని అద\nలించాడు. గుఱ్జం వాయువేగంతో కాలప\nఆవతలి ఒడ్డుకు దూకింది. కాసేపు\nవిశాంతి తీసుకుని రాజకుమారుడు కోట\nవాకిలి దగ్గరికి పోయాడు.\n\nసన్యాసి చెప్పినట్లుగానే కోట గుమ్మం\nదగ్గిర ఒక మేక, ఆ దగ్గర్లోనే ఒక గడ్డి\nమోపూ కనిపించినై. రాజకుమారుడు\nగడ్డిమోపు మేకముందు పడేశాడు. మోపు\nకింద పడి పడటంతోలే అది మూడు\nతోడేళ్లుగా మారింది. రాజకుమారుడి\nవెంటవున్న వేటకుక్క ఒక్కసారి ఆ\nతోడేళ్లమీదికి దూకింది. మూడు తోడేళ్లూ\nఅమాంతం మేకమీదపడి దాన్ని నేట\nకరుచుకొని వెనక్కి తిరిగిచూడకుండా\nకొండవైపుకు పరిగెత్తిపోయినై.\n\nతర్వాత రాజకుమారుడు యింటి ఆవ\nరణలో ప్రవేశించాడు. సన్యాసి చెప్పినట్లు\nగానే ఆక్కడ మూడు కోళ్లూ, ఆ దగ్గర్లోనే\nధాన్యం కనిపించాయి. రాజకుమారుడు\nధాన్యం కోళ్లముందు చల్లాడు. ధాన్యం\nనేలమీద పడటంతోలే మూడు పిల్లులుగా\nమారింది. కుక్క మళ్లీ వాటిమీదికి\nదూకింది. మూడు పిల్లులూచేరి కోళ్లని\nనేటకరచుకుని కొండవైపుకు పరిగెత్తి\nపోయినై.\n\nపై రెండు వింతలూ చూసేసరికి రాజ\nకుమారుడికి కోటలో ప్రవేశిస్తే ఏమి వింత\nజరుగుతుందో కూడా తెలుసుకోవాలిని\nకుతూహలం కలిగింది. కాని 'ముగ్గురూ\nఒక్కసారి చస్తారు!' అని సన్యాసి భయ\nపెట్టటంపల్ల రాజకుమారుడికి కోటలో\nప్రవేసించబానికి మొదట ధైర్యం చాల\nలేదు. కాని అంతకంతకీ, ఏమి వింత\nజరుగుతుందో తెలుసుకోవాలనే కుతూ\nహలం జాస్తి కాసాగింది. అందువల్ల,\n“ఏమౌతే ఆది అవుతుంది” అని ధైర్యం\nతెచ్చుకుని రాజకుమారుడు గుజ్జాన్ని\nకుక్కనీ ఆవరణలో వదిలే కోటలో\nప్రవేశించబోయాడు.\n\nచంద్రమామ\n\nరాజకుమారుడు కొటతలుపు తోసి లోపల ప్రవేశించాడు. అది ఒక పెద్ద విశాలమైనమహలు. అంతాచికటి గబ్బ గయ్యంగా వుంది. కన్ను పాడుచుకన్నాడారి విమాత్రం కనిపించటంలేదు. ఐనా రాజకుమారుడు తడువుకుంటూ ధైర్యంగా నడక సాగించాడు. అలా పోగా పోగా చివరికి అతనికి ఒక గది కనిపించింది. గది తలుపులు వేసివున్నయే. కాని తాళంవేసి బెజ్జం లోంచి సన్నని కాంతి బయటికి వస్తోంది. అ కాంతివల్ల దారి యిప్పుడు కొంచెం తెలుస్తూపుంది. రాజకుమారుడు ఎకాఏకిని గదితలుపు తోసుకుని లోపల ప్రవేశించాడు. గదిలో ఒక హంసతూరికాతల్పం వుంది. దానిమీద ఒక అప్సరసాటి కన్య నిద్రపోతూ వుంది. రాజకుమారుడు ఆమెని లేవుదామని కాలితో నేల మీద తన్ని చప్పుడు చేశాడు. కాని ఆమెలేవలేదు. రాజకుమారుడు దగ్గరికిపోయి మీద చెయ్యివేసి లేపాడు. కాని ఆమెలేవలేదు. మరోసారి గట్టిగా తట్టి చూశాడు. అప్పటిక ఆమెలేవలేదు. ఇంతలో రాజకుమారుడి దృష్టి ఆ కన్య చెవిలో వున్న ఒక తెల్ల గులాచిపువ్వుమీద పడింది.\n\nCHITRA\n\nరాజకుమారుడు ఆ పువ్వును తీశాడు. పువ్వు తీసివెయ్యగానే ఆ కన్య ఒక్కసారిగా లేచి కూర్చుంది. రాజకుమారుడూ, ఆమె ఒక్కనిమిషం ఒకరి నొకరు ఆశ్చర్యంగా చూసుకున్నారు.\n\nతర్వాత ఆమె రాజకుమారుణ్ణి ఆడిగి అత నక్కడికి ఎలా వచ్చింది. ఏమి జరిగిందీ అంతా తెలుసుకుంది. తర్వాత రాజకుమారుడు ఆమెని తన సంగతి చెప్పమనికోరాడు. అప్పుడు ఆమె ఇలా చెప్పటం మొదలెట్టింది.\n\n\" నిన్ను ఇక్కడికి తీసుకొచ్చిన సన్యాసి నిజానికి సన్యాసి కాడు. అతనొక మాయల మారి రాకసుడు. అతను మనుష్యుల గుండెకాయలను తిని జీవిస్తాడు. ఏమని షిని బడితే ఆ మని షిని చంపలేదు. అతను చెప్పినపని ఎవరైతే చెయ్యము అని అంటారో వాళ్లనే అతను చంపగలడు. అతను చెప్పిపనులు చాల భయంకరము గానూ, కష్టంగానూ వుంటైగనుక ఎవరూ చెయ్యమంటారు. అట్లా అన్నవారిని చంపి వాళ్ల గుండెకాయ తింటాడు. ఒకవేళ ఎవ రైనా అతను చెప్పినపని చెయ్యగలిగా రంటే, వాళ్ళకు యింకోపని, అదిచేస్తే యింకోపని, యిలా ఒకదానికంటే ఒకటి కరినంగా వుండేపనులు చెబుతాడు. ఇన్ని పనులలో ఏదో వక్కపని అయినా అ వచ్చిన వాళ్లు 'మేము చెయ్యము' అనేటంత భయంకరంగా వుంటుంది. వాళ్ళు అలా అనగానే అతనికి వాళ్లని చంపగలశక్తి\n\nవస్తుంది. ఇప్పటికి చాలామంది దురదృష్టి వంతులు యితని చేతులో చనిపోయారు. నేను కూడా ఒక గొప్ప రాచబిడ్డనే. నీ మాదిరిగానే సన్ను కూడా ఈ రాకసుడు నా తలిదండ్రుల దగ్గిర్నించి తెచ్చాడు. కాని, నా ఆదృష్టవశాత్తు అతనికి నా మీద ప్రేమ కలిగింది. అందుచేత అందర్నీ చంపినట్లు నన్నుచంపలేదు. అతను జైటికి వెళ్లేటప్పుడు ఈ తెల్ల గులాబిపువ్వు నా చెవిలో పెడతాడు. అదికూడా ఒక మాయ పువ్వే. అది నాచెవిలో పెట్టగానే నేను ఒళ్లు తెలియకుండా యిలా పడుకుండిపోతాను. అతను మళ్లీ తిరిగివచ్చి పువ్వు తీసేవరకూ యిలాగే పడుకుంటాను. ఇంక కాసేపట్లో అతను తిరిగివస్తాడు. అతను పచ్చేసరికి సుప్రువ పుష్పును నా చెవిలో పెట్టి, నీవు వెళ్లి మళ్లీ బయటి ఆవరణులో కూర్చునివుండాలి. ఇకపో,\" అని చెప్పింది.\n\n[ఇంకా వుంది]"
        },
        {
            "title": "బాలగేయాలు",
            "page_start": 45,
            "author": "వెలగా రామకోటయ్యచౌదరి",
            "pdf_page": 46,
            "content": "బాలగేయాలు\n\nనంపాదన ।\n\nవెలగా రామకోటయ్యుచౌదరి, మాచవరం\n\n1\n\nసిరిసిరివానలు కురియంగా\nసీతాదేవి పుట్టంగా\nరాపణాసురుని తలగొట్టంగా\nరంగులరాట్నం తిరగంగా\n\n2\n\nదిబ్బగుంటలో తిరణాలంట\nడబ్బుకి మానెడు శనగాలంట\nఆడపిల్లకు ఆద్దాలంట\nమొగపిల్లోడికి మొల్గుడట\nచంకపిల్లకు టెంకాయంట\nకడుపులో పిల్లకు కరక్కాయంట\n\n3\n\nవిటిఅవతల ఎర్రజొన్నకర\nవచ్చే జోయే పనియావు మేసె\nపనియావు కడుపున చార్లపెయ్య\nచార్లపెయ్యకు పండ్లేలేవు\nఅల్లా రల్లారే.\n\n48-వ పేజీలోని పొడువు పద్యములభి జవాబు\n1. గుడిలో గంట; 2. పాలు\n\nచోటమూమీ\nపెజీల్\n(భాషాభవుడ్డకి)\n\nఆ ధారములు\n\nఅర్హము :\n\n1. చివర\n\n3. కెరటము\n\n5. పెండ్లి కొమారుడు\n\n7. చెయ్యి\n\n9. మింగటంలో\nఒకరకం\n\n11. మనముతలకు రాచుకునేది\n\n13. గడ్డి - గాదం\n\n15. నటించేచాడు\n\n16. పసిపిల్లలకు - ఇది తప్పక\nకావాలి\n\n17. కూరమ్మగము\n\nతు\n\nము\n\nగు\n\nక\n\nల\n\nపా\n\nమి\n\nచూ\n\nచూ\n\nచూ\n\nచూ\n\nచూ\n\nచూ\n\nచూ\n\nచూ\n\nచూ\n\nచూ\n\nచూ\n\nచూ\n\nచూ\n\nచూ\n\nచూ\n\nచూ\n\nచూ\n\nచూ\n\nచూ\n\nచూ\n\nచూ\n\nచూ\n\nచూ\n\nచూ\n\nచూ\n\nచూ\n\nచూ\n\nచూ\n\nచూ\n\nచూ\n\nచూ\n\nచూ\n\nచూ\n\nచూ\n\nచూ\n\nచూ\n\nచూ\n\nచూ\n\nచూ\n\nచూ\n\nచూ\n\nచూ\n\nచూ\n\nచూ\n\nచూ\n\nచూ\n\nచూ\n\nచూ\n\nచూ\n\nచూ\n\nచూ\n\nచూ\n\nచూ\n\nచూ\n\nచూ\n\nచూ\n\nచూ\n\nచూ\n\nచూ\n\nచూ\n\nచూ\n\nచూ\n\nచూ\n\nచూ\n\nచూ\n\nచూ\n\nచూ\n\nచూ\n\nచూ\n\nచూ\n\nచూ\n\nచూ\n\nచూ\n\nచూ\n\nచూ\n\nచూ\n\nచూ\n\nచూ\n\nచూ\n\nచూ\n\nచూ\n\nచూ\n\nచూ\n\nచూ\n\nచూ\n\nచూ\n\nచూ\n\nచూ\n\nచూ\n\nచూ\n\nచూ\n\nచూ\n\nచూ\n\nచూ\n\nచూ\n\nచూ\n\nచూ\n\nచూ\n\nచూ\n\nచూ\n\nచూ\n\nచూ\n\nచూ\n\nచూ\n\nచూ\n\nచూ\n\nచూ\n\nచూ\n\nచూ\n\nచూ\n\nచూ\n\nచూ\n\nచూ\n\nచూ\n\nచూ\n\nచూ\n\nచూ\n\nచూ\n\nచూ\n\nచూ\n\nచూ\n\nచూ\n\nచూ\n\nచూ\n\nచూ\n\nచూ\n\nచూ\n\nచూ\n\nచూ\n\nచూ\n\nచూ\n\nచూ\n\nచూ\n\nచూ\n\nచూ\n\nచూ\n\nచూ\n\nచూ\n\nచూ\n\nచూ\n\nచూ\n\nచూ\n\nచూ\n\nచూ\n\nచూ\n\nచూ\n\nచూ\n\nచూ\n\nచూ\n\nచూ\n\nచూ\n\nచూ\n\nచూ\n\nచూ\n\nచూ\n\nచూ\n\nచూ\n\nచూ\n\nచూ\n\nచూ\n\nచూ\n\nచూ\n\nచూ\n\nచూ\n\nచూ\n\nచూ\n\nచూ\n\nచూ\n\nచూ\n\nచూ\n\nచూ\n\nచూ\n\nచూ\n\nచూ\n\nచూ\n\nచూ\n\nచూ\n\nచూ\n\nచూ\n\nచూ\n\nచూ\n\nచూ\n\nచూ\n\nచూ\n\nచూ\n\nచూ\n\nచూ\n\nచూ\n\nచూ\n\nచూ\n\nచూ\n\nచూ\n\nచూ\n\nచూ\n\nచూ\n\nచూ\n\nచూ\n\nచూ\n\nచూ\n\nచూ\n\nచూ\n\nచూ\n\nచూ\n\nచూ\n\nచూ\n\nచూ\n\nచూ\n\nచూ\n\nచూ\n\nచూ\n\nచూ\n\nచూ\n\nచూ\n\nచూ\n\nచూ\n\nచూ\n\nచూ\n\nచూ\n\nచూ\n\nచూ\n\nచూ\n\nచూ\n\nచూ\n\nచూ\n\nచూ\n\nచూ\n\nచూ\n\nచూ\n\nచూ\n\nచూ\n\nచూ\n\nచూ\n\nచూ\n\nచూ\n\nచూ\n\nచూ\n\nచూ\n\nచూ\n\nచూ\n\nచూ\n\nచూ\n\nచూ\n\nచూ\n\nచూ\n\nచూ\n\nచూ\n\nచూ\n\nచూ\n\nచూ\n\nచూ\n\nచూ\n\nచూ\n\nచూ\n\nచూ\n\nచూ\n\nచూ\n\nచూ\n\nచూ\n\nచూ\n\nచూ\n\nచూ\n\nచూ\n\nచూ\n\nచూ\n\nచూ\n\nచూ\n\nచూ\n\nచూ\n\nచూ\n\nచూ\n\nచూ\n\nచూ\n\nచూ\n\nచూ\n\nచూ\n\nచూ\n\nచూ\n\nచూ\n\nచూ\n\nచూ\n\nచూ\n\nచూ\n\nచూ\n\nచూ\n\nచూ\n\nచూ\n\nచూ\n\nచూ\n\nచూ\n\nచూ\n\nచూ\n\nచూ\n\nచూ\n\nచూ\n\nచూ\n\nచూ\n\nచూ\n\nచూ\n\nచూ\n\nచూ\n\nచూ\n\nచూ\n\nచూ\n\nచూ\n\nచూ\n\nచూ\n\nచూ\n\nచూ\n\nచూ\n\nచూ\n\nచూ\n\nచూ\n\nచూ\n\nచూ\n\nచూ\n\nచూ\n\nచూ\n\nచూ\n\nచూ\n\nచూ\n\nచూ\n\nచూ\n\nచూ\n\nచూ\n\nచూ\n\nచూ\n\nచూ\n\nచూ\n\nచూ\n\nచూ\n\nచూ\n\nచూ\n\nచూ\n\nచూ\n\nచూ\n\nచూ\n\nచూ\n\nచూ\n\nచూ\n\nచూ\n\nచూ\n\nచూ\n\nచూ\n\nచూ\n\nచూ\n\nచూ\n\nచూ\n\nచూ\n\nచూ\n\nచూ\n\nచూ\n\nచూ\n\nచూ\n\nచూ\n\nచూ\n\nచూ\n\nచూ\n\nచూ\n\nచూ\n\nచూ\n\nచూ\n\nచూ\n\nచూ\n\nచూ\n\nచూ\n\nచూ\n\nచూ\n\nచూ\n\nచూ\n\nచూ\n\nచూ\n\nచూ\n\nచూ\n\nచూ\n\nచూ\n\nచూ\n\nచూ\n\nచూ\n\nచూ\n\nచూ\n\nచూ\n\nచూ\n\nచూ\n\nచూ\n\nచూ\n\nచూ\n\nచూ\n\nచూ\n\nచూ\n\nచూ\n\nచూ\n\nచూ\n\nచూ\n\nచూ\n\nచూ\n\nచూ\n\nచూ\n\nచూ\n\nచూ\n\nచూ\n\nచూ\n\nచూ\n\nచూ\n\nచూ\n\nచూ\n\nచూ\n\nచూ\n\nచూ\n\nచూ\n\nచూ\n\nచూ\n\nచూ\n\nచూ\n\nచూ\n\nచూ\n\nచూ\n\nచూ\n\nచూ\n\nచూ\n\nచూ\n\nచూ\n\nచూ\n\nచూ\n\nచూ\n\nచూ\n\nచూ\n\nచూ\n\nచూ\n\nచూ\n\nచూ\n\nచూ\n\nచూ\n\nచూ\n\nచూ\n\nచూ\n\nచూ\n\nచూ\n\nచూ\n\nచూ\n\nచూ\n\nచూ\n\nచూ\n\nచూ\n\nచూ\n\nచూ\n\nచూ\n\nచూ\n\nచూ\n\nచూ\n\nచూ\n\nచూ\n\nచూ\n\nచూ\n\nచూ\n\nచూ\n\nచూ\n\nచూ\n\nచూ\n\nచూ\n\nచూ\n\nచూ\n\nచూ\n\nచూ\n\nచూ\n\nచూ\n\nచూ\n\nచూ\n\nచూ\n\nచూ\n\nచూ\n\nచూ\n\nచూ\n\nచూ\n\nచూ\n\nచూ\n\nచూ\n\nచూ\n\nచూ\n\nచూ\n\nచూ\n\nచూ\n\nచూ\n\nచూ\n\nచూ\n\nచూ\n\nచూ\n\nచూ\n\nచూ\n\nచూ\n\nచూ\n\nచూ\n\nచూ\n\nచూ\n\nచూ\n\nచూ\n\nచూ\n\nచూ\n\nచూ\n\nచూ\n\nచూ\n\nచూ\n\nచూ\n\nచూ\n\nచూ\n\nచూ\n\nచూ\n\nచూ\n\nచూ\n\nచూ\n\nచూ\n\nచూ\n\nచూ\n\nచూ\n\nచూ\n\nచూ\n\nచూ\n\nచూ\n\nచూ\n\nచూ\n\nచూ\n\nచూ\n\nచూ\n\nచూ\n\nచూ\n\nచూ\n\nచూ\n\nచూ\n\nచూ\n\nచూ\n\nచూ\n\nచూ\n\nచూ\n\nచూ\n\nచూ\n\nచూ\n\nచూ\n\nచూ\n\nచూ\n\nచూ\n\nచూ\n\nచూ\n\nచూ\n\nచూ\n\nచూ\n\nచూ\n\nచూ\n\nచూ\n\nచూ\n\nచూ\n\nచూ\n\nచూ\n\nచూ\n\nచూ\n\nచూ\n\nచూ\n\nచూ\n\nచూ\n\nచూ\n\nచూ\n\nచూ\n\nచూ\n\nచూ\n\nచూ\n\nచూ\n\nచూ\n\nచూ\n\nచూ\n\nచూ\n\nచూ\n\nచూ\n\nచూ\n\nచూ\n\nచూ\n\nచూ\n\nచూ\n\nచూ\n\nచూ\n\nచూ\n\nచూ\n\nచూ\n\nచూ\n\nచూ\n\nచూ\n\nచూ\n\nచూ\n\nచూ\n\nచూ\n\nచూ\n\nచూ\n\nచూ\n\nచూ\n\nచూ\n\nచూ\n\nచూ\n\nచూ\n\nచూ\n\nచూ\n\nచూ\n\nచూ\n\nచూ\n\nచూ\n\nచూ\n\nచూ\n\nచూ\n\nచూ\n\nచూ\n\nచూ\n\nచూ\n\nచూ\n\nచూ\n\nచూ\n\nచూ\n\nచూ\n\nచూ\n\nచూ\n\nచూ\n\nచూ\n\nచూ\n\nచూ\n\nచూ\n\nచూ\n\nచూ\n\nచూ\n\nచూ\n\nచూ\n\nచూ\n\nచూ\n\nచూ\n\nచూ\n\nచూ\n\nచూ\n\nచూ\n\nచూ\n\nచూ\n\nచూ\n\nచూ\n\nచూ\n\nచూ\n\nచూ\n\nచూ\n\nచూ\n\nచూ\n\nచూ\n\nచూ\n\nచూ\n\nచూ\n\nచూ\n\nచూ\n\nచూ\n\nచూ\n\nచూ\n\nచూ\n\nచూ\n\nచూ\n\nచూ\n\nచూ\n\nచూ\n\nచూ\n\nచూ\n\nచూ\n\nచూ\n\nచూ\n\nచూ\n\nచూ\n\nచూ\n\nచూ\n\nచూ\n\nచూ\n\nచూ\n\nచూ\n\nచూ\n\nచూ\n\nచూ\n\nచూ\n\nచూ\n\nచూ\n\nచూ\n\nచూ\n\nచూ\n\nచూ\n\nచూ\n\nచూ\n\nచూ\n\nచూ\n\nచూ\n\nచూ\n\nచూ\n\nచూ\n\nచూ\n\nచూ\n\nచూ\n\nచూ\n\nచూ\n\nచూ\n\nచూ\n\nచూ\n\nచూ\n\nచూ\n\nచూ\n\nచూ\n\nచూ\n\nచూ\n\nచూ\n\nచూ\n\nచూ\n\nచూ\n\nచూ\n\nచూ\n\nచూ\n\nచూ\n\nచూ\n\nచూ\n\nచూ\n\nచూ\n\nచూ\n\nచూ\n\nచూ\n\nచూ\n\nచూ\n\nచూ\n\nచూ\n\nచూ\n\nచూ\n\nచూ\n\nచూ\n\nచూ\n\nచూ\n\nచూ\n\nచూ\n\nచూ\n\nచూ\n\nచూ\n\nచూ\n\nచూ\n\nచూ\n\nచూ\n\nచూ\n\nచూ\n\nచూ\n\nచూ\n\nచూ\n\nచూ\n\nచూ\n\nచూ\n\nచూ\n\nచూ\n\nచూ\n\nచూ\n\nచూ\n\nచూ\n\nచూ\n\nచూ\n\nచూ\n\nచూ\n\nచూ\n\nచూ\n\nచూ\n\nచూ\n\nచూ\n\nచూ\n\nచూ\n\nచూ\n\nచూ\n\nచూ\n\nచూ\n\nచూ\n\nచూ\n\nచూ\n\nచూ\n\nచూ\n\nచూ\n\nచూ\n\nచూ\n\nచూ\n\nచూ\n\nచూ\n\nచూ\n\nచూ\n\nచూ\n\nచూ\n\nచూ\n\nచూ\n\nచూ\n\nచూ\n\nచూ\n\nచూ\n\nచూ\n\nచూ\n\nచూ\n\nచూ\n\nచూ\n\nచూ\n\nచూ\n\nచూ\n\nచూ\n\nచూ\n\nచూ\n\nచూ\n\nచూ\n\nచూ\n\nచూ\n\nచూ\n\nచూ\n\nచూ\n\nచూ\n\nచూ\n\nచూ\n\nచూ\n\nచూ\n\nచూ\n\nచూ\n\nచూ\n\nచూ\n\nచూ\n\nచూ\n\nచూ\n\nచూ\n\nచూ\n\nచూ\n\nచూ\n\nచూ\n\nచూ\n\nచూ\n\nచూ\n\nచూ\n\nచూ\n\nచూ\n\nచూ\n\nచూ\n\nచూ\n\nచూ\n\nచూ\n\nచూ\n\nచూ\n\nచూ\n\nచూ\n\nచూ\n\nచూ\n\nచూ\n\nచూ\n\nచూ\n\nచూ\n\nచూ\n\nచూ\n\nచూ\n\nచూ\n\nచూ\n\nచూ\n\nచూ\n\nచూ\n\nచూ\n\nచూ\n\nచూ\n\nచూ\n\nచూ\n\nచూ\n\nచూ\n\nచూ\n\nచూ\n\nచూ\n\nచూ\n\nచూ\n\nచూ\n\nచూ\n\nచూ\n\nచూ\n\nచూ\n\nచూ\n\nచూ\n\nచూ\n\nచూ\n\nచూ\n\nచూ\n\nచూ\n\nచూ\n\nచూ\n\nచూ\n\nచూ\n\nచూ\n\nచూ\n\nచూ\n\nచూ\n\nచూ\n\nచూ\n\nచూ\n\nచూ\n\nచూ\n\nచూ\n\nచూ\n\nచూ\n\nచూ\n\nచూ\n\nచూ\n\nచూ\n\nచూ\n\nచూ\n\nచూ\n\nచూ\n\nచూ\n\nచూ\n\nచూ\n\nచూ\n\nచూ\n\nచూ\n\nచూ\n\nచూ\n\nచూ\n\nచూ\n\nచూ\n\nచూ\n\nచూ\n\nచూ\n\nచూ\n\nచూ\n\nచూ\n\nచూ\n\nచూ\n\nచూ\n\nచూ\n\nచూ\n\nచూ\n\nచూ\n\nచూ\n\nచూ\n\nచూ\n\nచూ\n\nచూ\n\nచూ\n\nచూ\n\nచూ\n\nచూ\n\nచూ\n\nచూ\n\nచూ\n\nచూ\n\nచూ\n\nచూ\n\nచూ\n\nచూ\n\nచూ\n\nచూ\n\nచూ\n\nచూ\n\nచూ\n\nచూ\n\nచూ\n\nచూ\n\nచూ\n\nచూ\n\nచూ\n\nచూ\n\nచూ\n\nచూ\n\nచూ\n\nచూ\n\nచూ\n\nచూ\n\nచూ\n\nచూ\n\nచూ\n\nచూ\n\nచూ\n\nచూ\n\nచూ\n\nచూ\n\nచూ\n\nచూ\n\nచూ\n\nచూ\n\nచూ\n\nచూ\n\nచూ\n\nచూ\n\nచూ\n\nచూ\n\nచూ\n\nచూ\n\nచూ\n\nచూ\n\nచూ\n\nచూ\n\nచూ\n\nచూ\n\nచూ\n\nచూ\n\nచూ\n\nచూ\n\nచూ\n\nచూ\n\nచూ\n\nచూ\n\nచూ\n\nచూ\n\nచూ\n\nచూ\n\nచూ\n\nచూ\n\nచూ\n\nచూ\n\nచూ\n\nచూ\n\nచూ\n\nచూ\n\nచూ\n\nచూ\n\nచూ\n\nచూ\n\nచూ\n\nచూ\n\nచూ\n\nచూ\n\nచూ\n\nచూ\n\nచూ\n\nచూ\n\nచూ\n\nచూ\n\nచూ\n\nచూ\n\nచూ\n\nచూ\n\nచూ\n\nచూ\n\nచూ\n\nచూ\n\nచూ\n\nచూ\n\nచూ\n\nచూ\n\nచూ\n\nచూ\n\nచూ\n\nచూ\n\nచూ\n\nచూ\n\nచూ\n\nచూ\n\nచూ\n\nచూ\n\nచూ\n\nచూ\n\nచూ\n\nచూ\n\nచూ\n\nచూ\n\nచూ\n\nచూ\n\nచూ\n\nచూ\n\nచూ\n\nచూ\n\nచూ\n\nచూ\n\nచూ\n\nచూ\n\nచూ\n\nచూ\n\nచూ\n\nచూ\n\nచూ\n\nచూ\n\nచూ\n\nచూ\n\nచూ\n\nచూ\n\nచూ\n\nచూ\n\nచూ\n\nచూ\n\nచూ\n\nచూ\n\nచూ\n\nచూ\n\nచూ\n\nచూ\n\nచూ\n\nచూ\n\nచూ\n\nచూ\n\nచూ\n\nచూ\n\nచూ\n\nచూ\n\nచూ\n\nచూ\n\nచూ\n\nచూ\n\nచూ\n\nచూ\n\nచూ\n\nచూ\n\nచూ\n\nచూ\n\nచూ\n\nచూ\n\nచూ\n\nచూ\n\nచూ\n\nచూ\n\nచూ\n\nచూ\n\nచూ\n\nచూ\n\nచూ\n\nచూ\n\nచూ\n\nచూ\n\nచూ\n\nచూ\n\nచూ\n\nచూ\n\nచూ\n\nచూ\n\nచూ\n\nచూ\n\nచూ\n\nచూ\n\nచూ\n\nచూ\n\nచూ\n\nచూ\n\nచూ\n\nచూ\n\nచూ\n\nచూ\n\nచూ\n\nచూ\n\nచూ\n\nచూ\n\nచూ\n\nచూ\n\nచూ\n\nచూ\n\nచూ\n\nచూ\n\nచూ\n\nచూ\n\nచూ\n\nచూ\n\nచూ\n\nచూ\n\nచూ\n\nచూ\n\nచూ\n\nచూ\n\nచూ\n\nచూ\n\nచూ\n\nచూ\n\nచూ\n\nచూ\n\nచూ\n\nచూ\n\nచూ\n\nచూ\n\nచూ\n\nచూ\n\nచూ\n\nచూ\n\nచూ\n\nచూ\n\nచూ\n\nచూ\n\nచూ\n\nచూ\n\nచూ\n\nచూ\n\nచూ\n\nచూ\n\nచూ\n\nచూ\n\nచూ\n\nచూ\n\nచూ\n\nచూ\n\nచూ\n\nచూ\n\nచూ\n\nచూ\n\nచూ\n\nచూ\n\nచూ\n\nచూ\n\nచూ\n\nచూ\n\nచూ\n\nచూ\n\nచూ\n\nచూ\n\nచూ\n\nచూ\n\nచూ\n\nచూ\n\nచూ\n\nచూ\n\nచూ\n\nచూ\n\nచూ\n\nచూ\n\nచూ\n\nచూ\n\nచూ\n\nచూ\n\nచూ\n\nచూ\n\nచూ\n\nచూ\n\nచూ\n\nచూ\n\nచూ\n\nచూ\n\nచూ\n\nచూ\n\nచూ\n\nచూ\n\nచూ\n\nచూ\n\nచూ\n\nచూ\n\nచూ\n\nచూ\n\nచూ\n\nచూ\n\nచూ\n\nచూ\n\nచూ\n\nచూ\n\nచూ\n\nచూ\n\nచూ\n\nచూ\n\nచూ\n\nచూ\n\nచూ\n\nచూ\n\nచూ\n\nచూ\n\nచూ\n\nచూ\n\nచూ\n\nచూ\n\nచూ\n\nచూ\n\nచూ\n\nచూ\n\nచూ\n\nచూ\n\nచూ\n\nచూ\n\nచూ\n\nచూ\n\nచూ\n\nచూ\n\nచూ\n\nచూ\n\nచూ\n\nచూ\n\nచూ\n\nచూ\n\nచూ\n\nచూ\n\nచూ\n\nచూ\n\nచూ\n\nచూ\n\nచూ\n\nచూ\n\nచూ\n\nచూ\n\nచూ\n\nచూ\n\nచూ\n\nచూ\n\nచూ\n\nచూ\n\nచూ\n\nచూ\n\nచూ\n\nచూ\n\nచూ\n\nచూ\n\nచూ\n\nచూ\n\nచూ\n\nచూ\n\nచూ\n\nచూ\n\nచూ\n\nచూ\n\nచూ\n\nచూ\n\nచూ\n\nచూ\n\nచూ\n\nచూ\n\nచూ\n\nచూ\n\nచూ\n\nచూ\n\nచూ\n\nచూ\n\nచూ\n\nచూ\n\nచూ\n\nచూ\n\nచూ\n\nచూ\n\nచూ\n\nచూ\n\nచూ\n\nచూ\n\nచూ\n\nచూ\n\nచూ\n\nచూ\n\nచూ\n\nచూ\n\nచూ\n\nచూ\n\nచూ\n\nచూ\n\nచూ\n\nచూ\n\nచూ\n\nచూ\n\nచూ\n\nచూ\n\nచూ\n\nచూ\n\nచూ\n\nచూ\n\nచూ\n\nచూ\n\nచూ\n\nచూ\n\nచూ\n\nచూ\n\nచూ\n\nచూ\n\nచూ\n\nచూ\n\nచూ\n\nచూ\n\nచూ\n\nచూ\n\nచూ\n\nచూ\n\nచూ\n\nచూ\n\nచూ\n\nచూ\n\nచూ\n\nచూ\n\nచూ\n\nచూ\n\nచూ\n\nచూ\n\nచూ\n\nచూ\n\nచూ\n\nచూ\n\nచూ\n\nచూ\n\nచూ\n\nచూ\n\nచూ\n\nచూ\n\nచూ\n\nచూ\n\nచూ\n\nచూ\n\nచూ\n\nచూ\n\nచూ\n\nచూ\n\nచూ\n\nచూ\n\nచూ\n\nచూ\n\nచూ\n\nచూ\n\nచూ\n\nచూ\n\nచూ\n\nచూ\n\nచూ\n\nచూ\n\nచూ\n\nచూ\n\nచూ\n\nచూ\n\nచూ\n\nచూ\n\nచూ\n\nచూ\n\nచూ\n\nచూ\n\nచూ\n\nచూ\n\nచూ\n\nచూ\n\nచూ\n\nచూ\n\nచూ\n\nచూ\n\nచూ\n\nచూ\n\nచూ\n\nచూ\n\nచూ\n\nచూ\n\nచూ\n\nచూ\n\nచూ\n\nచూ\n\nచూ\n\nచూ\n\nచూ\n\nచూ\n\nచూ\n\nచూ\n\nచూ\n\nచూ\n\nచూ\n\nచూ\n\nచూ\n\nచూ\n\nచూ\n\nచూ\n\nచూ\n\nచూ\n\nచూ\n\nచూ\n\nచూ\n\nచూ\n\nచూ\n\nచూ\n\nచూ\n\nచూ\n\nచూ\n\nచూ\n\nచూ\n\nచూ\n\nచూ\n\nచూ\n\nచూ\n\nచూ\n\nచూ\n\nచూ\n\nచూ\n\nచూ\n\nచూ\n\nచూ\n\nచూ\n\nచూ\n\nచూ\n\nచూ\n\nచూ\n\nచూ\n\nచూ\n\nచూ\n\nచూ\n\nచూ\n\nచూ\n\nచూ\n\nచూ\n\nచూ\n\nచూ\n\nచూ\n\nచూ\n\nచూ\n\nచూ\n\nచూ\n\nచూ\n\nచూ\n\nచూ\n\nచూ\n\nచూ\n\nచూ\n\nచూ\n\nచూ\n\nచూ\n\nచూ\n\nచూ\n\nచూ\n\nచూ\n\nచూ\n\nచూ\n\nచూ\n\nచూ\n\nచూ\n\nచూ\n\nచూ\n\nచూ\n\nచూ\n\nచూ\n\nచూ\n\nచూ\n\nచూ\n\nచూ\n\nచూ\n\nచూ\n\nచూ\n\nచూ\n\nచూ\n\nచూ\n\nచూ\n\nచూ\n\nచూ\n\nచూ\n\nచూ\n\nచూ\n\nచూ\n\nచూ\n\nచూ\n\nచూ\n\nచూ\n\nచూ\n\nచూ\n\nచూ\n\nచూ\n\nచూ\n\nచూ\n\nచూ\n\nచూ\n\nచూ\n\nచూ\n\nచూ\n\nచూ\n\nచూ\n\nచూ\n\nచూ\n\nచూ\n\nచూ\n\nచూ\n\nచూ\n\nచూ\n\nచూ\n\nచూ\n\nచూ\n\nచూ\n\nచూ\n\nచూ\n\nచూ\n\nచూ\n\nచూ\n\nచూ\n\nచూ\n\nచూ\n\nచూ\n\nచూ\n\nచూ\n\nచూ\n\nచూ\n\nచూ\n\nచూ\n\nచూ\n\nచూ\n\nచూ\n\nచూ\n\nచూ\n\nచూ\n\nచూ\n\nచూ\n\nచూ\n\nచూ\n\nచూ\n\nచూ\n\nచూ\n\nచూ\n\nచూ\n\nచూ\n\nచూ\n\nచూ\n\nచూ\n\nచూ\n\nచూ\n\nచూ\n\nచూ\n\nచూ\n\nచూ\n\nచూ\n\nచూ\n\nచూ\n\nచూ\n\nచూ\n\nచూ\n\nచూ\n\nచూ\n\nచూ\n\nచూ\n\nచూ\n\nచూ\n\nచూ\n\nచూ\n\nచూ\n\nచూ\n\nచూ\n\nచూ\n\nచూ\n\nచూ\n\nచూ\n\nచూ\n\nచూ\n\nచూ\n\nచూ\n\nచూ\n\nచూ\n\nచూ\n\nచూ\n\nచూ\n\nచూ\n\nచూ\n\nచూ\n\nచూ\n\nచూ\n\nచూ\n\nచూ\n\nచూ\n\nచూ\n\nచూ\n\nచూ\n\nచూ\n\nచూ\n\nచూ\n\nచూ\n\nచూ\n\nచూ\n\nచూ\n\nచూ\n\nచూ\n\nచూ\n\nచూ\n\nచూ\n\nచూ\n\nచూ\n\nచూ\n\nచూ\n\nచూ\n\nచూ\n\nచూ\n\nచూ\n\nచూ\n\nచూ\n\nచూ\n\nచూ\n\nచూ\n\nచూ\n\nచూ\n\nచూ\n\nచూ\n\nచూ\n\nచూ\n\nచూ\n\nచూ\n\nచూ\n\nచూ\n\nచూ\n\nచూ\n\nచూ\n\nచూ\n\nచూ\n\nచూ\n\nచూ\n\nచూ\n\nచూ\n\nచూ\n\nచూ\n\nచూ\n\nచూ\n\nచూ\n\nచూ\n\nచూ\n\nచూ\n\nచూ\n\nచూ\n\nచూ\n\nచూ\n\nచూ\n\nచూ\n\nచూ\n\nచూ\n\nచూ\n\nచూ\n\nచూ\n\nచూ\n\nచూ\n\nచూ\n\nచూ\n\nచూ\n\nచూ\n\nచూ\n\nచూ\n\nచూ\n\nచూ\n\nచూ\n\nచూ\n\nచూ\n\nచూ\n\nచూ\n\nచూ\n\nచూ\n\nచూ\n\nచూ\n\nచూ\n\nచూ\n\nచూ\n\nచూ\n\nచూ\n\nచూ\n\nచూ\n\nచూ\n\nచూ\n\nచూ\n\nచూ\n\nచూ\n\nచూ\n\nచూ\n\nచూ\n\nచూ\n\nచూ\n\nచూ\n\nచూ\n\nచూ\n\nచూ\n\nచూ\n\nచూ\n\nచూ\n\nచూ\n\nచూ\n\nచూ\n\nచూ\n\nచూ\n\nచూ\n\nచూ\n\nచూ\n\nచూ\n\nచూ\n\nచూ\n\nచూ\n\nచూ\n\nచూ\n\nచూ\n\nచూ\n\nచూ\n\nచూ\n\nచూ\n\nచూ\n\nచూ\n\nచూ\n\nచూ\n\nచూ\n\nచూ\n\nచూ\n\nచూ\n\nచూ\n\nచూ\n\nచూ\n\nచూ\n\nచూ\n\nచూ\n\nచూ\n\nచూ\n\nచూ\n\nచూ\n\nచూ\n\nచూ\n\nచూ\n\nచూ\n\nచూ\n\nచూ\n\nచూ\n\nచూ\n\nచూ\n\nచూ\n\nచూ\n\nచూ\n\nచూ\n\nచూ\n\nచూ\n\nచూ\n\nచూ\n\nచూ\n\nచూ\n\nచూ\n\nచూ\n\nచూ\n\nచూ\n\nచూ\n\nచూ\n\nచూ\n\nచూ\n\nచూ\n\nచూ\n\nచూ\n\nచూ\n\nచూ\n\nచూ\n\nచూ\n\nచూ\n\nచూ\n\nచూ\n\nచూ\n\nచూ\n\nచూ\n\nచూ\n\nచూ\n\nచూ\n\nచూ\n\nచూ\n\nచూ\n\nచూ\n\nచూ\n\nచూ\n\nచూ\n\nచూ\n\nచూ\n\nచూ\n\nచూ\n\nచూ\n\nచూ\n\nచూ\n\nచూ\n\nచూ\n\nచూ\n\nచూ\n\nచూ\n\nచూ\n\nచూ\n\nచూ\n\nచూ\n\nచూ\n\nచూ\n\nచూ\n\nచూ\n\nచూ\n\nచూ\n\nచూ\n\nచూ\n\nచూ\n\nచూ\n\nచూ\n\nచూ\n\nచూ\n\nచూ\n\nచూ\n\nచూ\n\nచూ\n\nచూ\n\nచూ\n\nచూ\n\nచూ\n\nచూ\n\nచూ\n\nచూ\n\nచూ\n\nచూ\n\nచూ\n\nచూ\n\nచూ\n\nచూ\n\nచూ\n\nచూ\n\nచూ\n\nచూ\n\nచూ\n\nచూ\n\nచూ\n\nచూ\n\nచూ\n\nచూ\n\nచూ\n\nచూ\n\nచూ\n\nచూ\n\nచూ\n\nచూ\n\nచూ\n\nచూ\n\nచూ\n\nచూ\n\nచూ\n\nచూ\n\nచూ\n\nచూ\n\nచూ\n\nచూ\n\nచూ\n\nచూ\n\nచూ\n\nచూ\n\nచూ\n\nచూ\n\nచూ\n\nచూ\n\nచూ\n\nచూ\n\nచూ\n\nచూ\n\nచూ\n\nచూ\n\nచూ\n\nచూ\n\nచూ\n\nచూ\n\nచూ\n\nచూ\n\nచూ\n\nచూ\n\nచూ\n\nచూ\n\nచూ\n\nచూ\n\nచూ\n\nచూ\n\nచూ\n\nచూ\n\nచూ\n\nచూ\n\nచూ\n\nచూ\n\nచూ\n\nచూ\n\nచూ\n\nచూ\n\nచూ\n\nచూ\n\nచూ\n\nచూ\n\nచూ\n\nచూ\n\nచూ\n\nచూ\n\nచూ\n\nచూ\n\nచూ\n\nచూ\n\nచూ\n\nచూ\n\nచూ\n\nచూ\n\nచూ\n\nచూ\n\nచూ\n\nచూ\n\nచూ\n\nచూ\n\nచూ\n\nచూ\n\nచూ\n\nచూ\n\nచూ\n\nచూ\n\nచూ\n\nచూ\n\nచూ\n\nచూ\n\nచూ\n\nచూ\n\nచూ\n\nచూ\n\nచూ\n\nచూ\n\nచూ\n\nచూ\n\nచూ\n\nచూ\n\nచూ\n\nచూ\n\nచూ\n\nచూ\n\nచూ\n\nచూ\n\nచూ\n\nచూ\n\nచూ\n\nచూ\n\nచూ\n\nచూ\n\nచూ\n\nచూ\n\nచూ\n\nచూ\n\nచూ\n\nచూ\n\nచూ\n\nచూ\n\nచూ\n\nచూ\n\nచూ\n\nచూ\n\nచూ\n\nచూ\n\nచూ\n\nచూ\n\nచూ\n\nచూ\n\nచూ\n\nచూ\n\nచూ\n\nచూ\n\nచూ\n\nచూ\n\nచూ\n\nచూ\n\nచూ\n\nచూ\n\nచూ\n\nచూ\n\nచూ\n\nచూ\n\nచూ\n\nచూ\n\nచూ\n\nచూ\n\nచూ\n\nచూ\n\nచూ\n\nచూ\n\nచూ\n\nచూ\n\nచూ\n\nచూ\n\nచూ\n\nచూ\n\nచూ\n\nచూ\n\nచూ\n\nచూ\n\nచూ\n\nచూ\n\nచూ\n\nచూ\n\nచూ\n\nచూ\n\nచూ\n\nచూ\n\nచూ\n\nచూ\n\nచూ\n\nచూ\n\nచూ\n\nచూ\n\nచూ\n\nచూ\n\nచూ\n\nచూ\n\nచూ\n\nచూ\n\nచూ\n\nచూ\n\nచూ\n\nచూ\n\nచూ\n\nచూ\n\nచూ\n\nచూ\n\nచూ\n\nచూ\n\nచూ\n\nచూ\n\nచూ\n\nచూ\n\nచూ\n\nచూ\n\nచూ\n\nచూ\n\nచూ\n\nచూ\n\nచూ\n\nచూ\n\nచూ\n\nచూ\n\nచూ\n\nచూ\n\nచూ\n\nచూ\n\nచూ\n\nచూ\n\nచూ\n\nచూ\n\nచూ\n\nచూ\n\nచూ\n\nచూ\n\nచూ\n\nచూ\n\nచూ\n\nచూ\n\nచూ\n\nచూ\n\nచూ\n\nచూ\n\nచూ\n\nచూ\n\nచూ\n\nచూ\n\nచూ\n\nచూ\n\nచూ\n\nచూ\n\nచూ\n\nచూ\n\nచూ\n\nచూ\n\nచూ\n\nచూ\n\nచూ\n\nచూ\n\nచూ\n\nచూ\n\nచూ\n\nచూ\n\nచూ\n\nచూ\n\nచూ\n\nచూ\n\nచూ\n\nచూ\n\nచూ\n\nచూ\n\nచూ\n\nచూ\n\nచూ\n\nచూ\n\nచూ\n\nచూ\n\nచూ\n\nచూ\n\nచూ\n\nచూ\n\nచూ\n\nచూ\n\nచూ\n\nచూ\n\nచూ\n\nచూ\n\nచూ\n\nచూ\n\nచూ\n\nచూ\n\nచూ\n\nచూ\n\nచూ\n\nచూ\n\nచూ\n\nచూ\n\nచూ\n\nచూ\n\nచూ\n\nచూ\n\nచూ\n\nచూ\n\nచూ\n\nచూ\n\nచూ\n\nచూ\n\nచూ\n\nచూ\n\nచూ\n\nచూ\n\nచూ\n\nచూ\n\nచూ\n\nచూ\n\nచూ\n\nచూ\n\nచూ\n\nచూ\n\nచూ\n\nచూ\n\nచూ\n\nచూ\n\nచూ\n\nచూ\n\nచూ\n\nచూ\n\nచూ\n\nచూ\n\nచూ\n\nచూ\n\nచూ\n\nచూ\n\nచూ\n\nచూ\n\nచూ\n\nచూ\n\nచూ\n\nచూ\n\nచూ\n\nచూ\n\nచూ\n\nచూ\n\nచూ\n\nచూ\n\nచూ\n\nచూ\n\nచూ\n\nచూ\n\nచూ\n\nచూ\n\nచూ\n\nచూ\n\nచూ\n\nచూ\n\nచూ\n\nచూ\n\nచూ\n\nచూ\n\nచూ\n\nచూ\n\nచూ\n\nచూ\n\nచూ\n\nచూ\n\nచూ\n\nచూ\n\nచూ\n\nచూ\n\nచూ\n\nచూ\n\nచూ\n\nచూ\n\nచూ\n\nచూ\n\nచూ\n\nచూ\n\nచూ\n\nచూ\n\nచూ\n\nచూ\n\nచూ\n\nచూ\n\nచూ\n\nచూ\n\nచూ\n\nచూ\n\nచూ\n\nచూ\n\nచూ\n\nచూ\n\nచూ\n\nచూ\n\nచూ\n\nచూ\n\nచూ\n\nచూ\n\nచూ\n\nచూ\n\nచూ\n\nచూ\n\nచూ\n\nచూ\n\nచూ\n\nచూ\n\nచూ\n\nచూ\n\nచూ\n\nచూ\n\nచూ\n\nచూ\n\nచూ\n\nచూ\n\nచూ\n\nచూ\n\nచూ\n\nచూ\n\nచూ\n\nచూ\n\nచూ\n\nచూ\n\nచూ\n\nచూ\n\nచూ\n\nచూ\n\nచూ\n\nచూ\n\nచూ\n\nచూ\n\nచూ\n\nచూ\n\nచూ\n\nచూ\n\nచూ\n\nచూ\n\nచూ\n\nచూ\n\nచూ\n\nచూ\n\nచూ\n\nచూ\n\nచూ\n\nచూ\n\nచూ\n\nచూ\n\nచూ\n\nచూ\n\nచూ\n\nచూ\n\nచూ\n\nచూ\n\nచూ\n\nచూ\n\nచూ\n\nచూ\n\nచూ\n\nచూ\n\nచూ\n\nచూ\n\nచూ\n\nచూ\n\nచూ\n\nచూ\n\nచూ\n\nచూ\n\nచూ\n\nచూ\n\nచూ\n\nచూ\n\nచూ\n\nచూ\n\nచూ\n\nచూ\n\nచూ\n\nచూ\n\nచూ\n\nచూ\n\nచూ\n\nచూ\n\nచూ\n\nచూ\n\nచూ\n\nచూ\n\nచూ\n\nచూ\n\nచూ\n\nచూ\n\nచూ\n\nచూ\n\nచూ\n\nచూ\n\nచూ\n\nచూ\n\nచూ\n\nచూ\n\nచూ\n\nచూ\n\nచూ\n\nచూ\n\nచూ\n\nచూ\n\nచూ\n\nచూ\n\nచూ\n\nచూ\n\nచూ\n\nచూ\n\nచూ\n\nచూ\n\nచూ\n\nచూ\n\nచూ\n\nచూ\n\nచూ\n\nచూ\n\nచూ\n\nచూ\n\nచూ\n\nచూ\n\nచూ\n\nచూ\n\nచూ\n\nచూ\n\nచూ\n\nచూ\n\nచూ\n\nచూ\n\nచూ\n\nచూ\n\nచూ\n\nచూ\n\nచూ\n\nచూ\n\nచూ\n\nచూ\n\nచూ\n\nచూ\n\nచూ\n\nచూ\n\nచూ\n\nచూ\n\nచూ\n\nచూ\n\nచూ\n\nచూ\n\nచూ\n\nచూ\n\nచూ\n\nచూ\n\nచూ\n\nచూ\n\nచూ\n\nచూ\n\nచూ\n\nచూ\n\nచూ\n\nచూ\n\nచూ\n\nచూ\n\nచూ\n\nచూ\n\nచూ\n\nచూ\n\nచూ\n\nచూ\n\nచూ\n\nచూ\n\nచూ\n\nచూ\n\nచూ\n\nచూ\n\nచూ\n\nచూ\n\nచూ\n\nచూ\n\nచూ\n\nచూ\n\nచూ\n\nచూ\n\nచూ\n\nచూ\n\nచూ\n\nచూ\n\nచూ\n\nచూ\n\nచూ\n\nచూ\n\nచూ\n\nచూ\n\nచూ\n\nచూ\n\nచూ\n\nచూ\n\nచూ\n\nచూ\n\nచూ\n\nచూ\n\nచూ\n\nచూ\n\nచూ\n\nచూ\n\nచూ\n\nచూ\n\nచూ\n\nచూ\n\nచూ\n\nచూ\n\nచూ\n\nచూ\n\nచూ\n\nచూ\n\nచూ\n\nచూ\n\nచూ\n\nచూ\n\nచూ\n\nచూ\n\nచూ\n\nచూ\n\nచూ\n\nచూ\n\nచూ\n\nచూ\n\nచూ\n\nచూ\n\nచూ\n\nచూ\n\nచూ\n\nచూ\n\nచూ\n\nచూ\n\nచూ\n\nచూ\n\nచూ\n\nచూ\n\nచూ\n\nచూ\n\nచూ\n\nచూ\n\nచూ\n\nచూ\n\nచూ\n\nచూ\n\nచూ\n\nచూ\n\nచూ\n\nచూ\n\nచూ\n\nచూ\n\nచూ\n\nచూ\n\nచూ\n\nచూ\n\nచూ\n\nచూ\n\nచూ\n\nచూ\n\nచూ\n\nచూ\n\nచూ\n\nచూ\n\nచూ\n\nచూ\n\nచూ\n\nచూ\n\nచూ\n\nచూ\n\nచూ\n\nచూ\n\nచూ\n\nచూ\n\nచూ\n\nచూ\n\nచూ\n\nచూ\n\nచూ\n\nచూ\n\nచూ\n\nచూ\n\nచూ\n\nచూ\n\nచూ\n\nచూ\n\nచూ\n\nచూ\n\nచూ\n\nచూ\n\nచూ\n\nచూ\n\nచూ\n\nచూ\n\nచూ\n\nచూ\n\nచూ\n\nచూ\n\nచూ\n\nచూ\n\nచూ\n\nచూ\n\nచూ\n\nచూ\n\nచూ\n\nచూ\n\nచూ\n\nచూ\n\nచూ\n\nచూ\n\nచూ\n\nచూ\n\nచూ\n\nచూ\n\nచూ\n\nచూ\n\nచూ\n\nచూ\n\nచూ\n\nచూ\n\nచూ\n\nచూ\n\nచూ\n\nచూ\n\nచూ\n\nచూ\n\nచూ\n\nచూ\n\nచూ\n\nచూ\n\nచూ\n\nచూ\n\nచూ\n\nచూ\n\nచూ\n\nచూ\n\nచూ\n\nచూ\n\nచూ\n\nచూ\n\nచూ\n\nచూ\n\nచూ\n\nచూ\n\nచూ\n\nచూ\n\nచూ\n\nచూ\n\nచూ\n\nచూ\n\nచూ\n\nచూ\n\nచూ\n\nచూ\n\nచూ\n\nచూ\n\nచూ\n\nచూ\n\nచూ\n\nచూ\n\nచూ\n\nచూ\n\nచూ\n\nచూ\n\nచూ\n\nచూ\n\nచూ\n\nచూ\n\nచూ\n\nచూ\n\nచూ\n\nచూ\n\nచూ\n\nచూ\n\nచూ\n\nచూ\n\nచూ\n\nచూ\n\nచూ\n\nచూ\n\nచూ\n\nచూ\n\nచూ\n\nచూ\n\nచూ\n\nచూ\n\nచూ\n\nచూ\n\nచూ\n\nచూ\n\nచూ\n\nచూ\n\nచూ\n\nచూ\n\nచూ\n\nచూ\n\nచూ\n\nచూ\n\nచూ\n\nచూ\n\nచూ\n\nచూ\n\nచూ\n\nచూ\n\nచూ\n\nచూ\n\nచూ\n\nచూ\n\nచూ\n\nచూ\n\nచూ\n\nచూ\n\nచూ\n\nచూ\n\nచూ\n\nచూ\n\nచూ\n\nచూ\n\nచూ\n\nచూ\n\nచూ\n\nచూ\n\nచూ\n\nచూ\n\nచూ\n\nచూ\n\nచూ\n\nచూ\n\nచూ\n\nచూ\n\nచూ\n\nచూ\n\nచూ\n\nచూ\n\nచూ\n\nచూ\n\nచూ\n\nచూ\n\nచూ\n\nచూ\n\nచూ\n\nచూ\n\nచూ\n\nచూ\n\nచూ\n\nచూ\n\nచూ\n\nచూ\n\nచూ\n\nచూ\n\nచూ\n\nచూ\n\nచూ\n\nచూ\n\nచూ\n\nచూ\n\nచూ\n\nచూ\n\nచూ\n\nచూ\n\nచూ\n\nచూ\n\nచూ\n\nచూ\n\nచూ\n\nచూ\n\nచూ\n\nచూ\n\nచూ\n\nచూ\n\nచూ\n\nచూ\n\nచూ\n\nచూ\n\nచూ\n\nచూ\n\nచూ\n\nచూ\n\nచూ\n\nచూ\n\nచూ\n\nచూ\n\nచూ\n\nచూ\n\nచూ\n\nచూ\n\nచూ\n\nచూ\n\nచూ\n\nచూ\n\nచూ\n\nచూ\n\nచూ\n\nచూ\n\nచూ\n\nచూ\n\nచూ\n\nచూ\n\nచూ\n\nచూ\n\nచూ\n\nచూ\n\nచూ\n\nచూ\n\nచూ\n\nచూ\n\nచూ\n\nచూ\n\nచూ\n\nచూ\n\nచూ\n\nచూ\n\nచూ\n\nచూ\n\nచూ\n\nచూ\n\nచూ\n\nచూ\n\nచూ\n\nచూ\n\nచూ\n\nచూ\n\nచూ\n\nచూ\n\nచూ\n\nచూ\n\nచూ\n\nచూ\n\nచూ\n\nచూ\n\nచూ\n\nచూ\n\nచూ\n\nచూ\n\nచూ\n\nచూ\n\nచూ\n\nచూ\n\nచూ\n\nచూ\n\nచూ\n\nచూ\n\nచూ\n\nచూ\n\nచూ\n\nచూ\n\nచూ\n\nచూ\n\nచూ\n\nచూ\n\nచూ\n\nచూ\n\nచూ\n\nచూ\n\nచూ\n\nచూ\n\nచూ\n\nచూ\n\nచూ\n\nచూ\n\nచూ\n\nచూ\n\nచూ\n\nచూ\n\nచూ\n\nచూ\n\nచూ\n\nచూ\n\nచూ\n\nచూ\n\nచూ\n\nచూ\n\nచూ\n\nచూ\n\nచూ\n\nచూ\n\nచూ\n\nచూ\n\nచూ\n\nచూ\n\nచూ\n\nచూ\n\nచూ\n\nచూ\n\nచూ\n\nచూ\n\nచూ\n\nచూ\n\nచూ\n\nచూ\n\nచూ\n\nచూ\n\nచూ\n\nచూ\n\nచూ\n\nచూ\n\nచూ\n\nచూ\n\nచూ\n\nచూ\n\nచూ\n\nచూ\n\nచూ\n\nచూ\n\nచూ\n\nచూ\n\nచూ\n\nచూ\n\nచూ\n\nచూ\n\nచూ\n\nచూ\n\nచూ\n\nచూ\n\nచూ\n\nచూ\n\nచూ\n\nచూ\n\nచూ\n\nచూ\n\nచూ\n\nచూ\n\nచూ\n\nచూ\n\nచూ\n\nచూ\n\nచూ\n\nచూ\n\nచూ\n\nచూ\n\nచూ\n\nచూ\n\nచూ\n\nచూ\n\nచూ\n\nచూ\n\nచూ\n\nచూ\n\nచూ\n\nచూ\n\nచూ\n\nచూ\n\nచూ\n\nచూ\n\nచూ\n\nచూ\n\nచూ\n\nచూ\n\nచూ\n\nచూ\n\nచూ\n\nచూ\n\nచూ\n\nచూ\n\nచూ\n\nచూ\n\nచూ\n\nచూ\n\nచూ\n\nచూ\n\nచూ\n\nచూ\n\nచూ\n\nచూ\n\nచూ\n\nచూ\n\nచూ\n\nచూ\n\nచూ\n\nచూ\n\nచూ\n\nచూ\n\nచూ\n\nచూ\n\nచూ\n\nచూ\n\nచూ\n\nచూ\n\nచూ\n\nచూ\n\nచూ\n\nచూ\n\nచూ\n\nచూ\n\nచూ\n\nచూ\n\nచూ\n\nచూ\n\nచూ\n\nచూ\n\nచూ\n\nచూ\n\nచూ\n\nచూ\n\nచూ\n\nచూ\n\nచూ\n\nచూ\n\nచూ\n\nచూ\n\nచూ\n\nచూ\n\nచూ\n\nచూ\n\nచూ\n\nచూ\n\nచూ\n\nచూ\n\nచూ\n\nచూ\n\nచూ\n\nచూ\n\nచూ\n\nచూ\n\nచూ\n\nచూ\n\nచూ\n\nచూ\n\nచూ\n\nచూ\n\nచూ\n\nచూ\n\nచూ\n\nచూ\n\nచూ\n\nచూ\n\nచూ\n\nచూ\n\nచూ\n\nచూ\n\nచూ\n\nచూ\n\nచూ\n\nచూ\n\nచూ\n\nచూ\n\nచూ\n\nచూ\n\nచూ\n\nచూ\n\nచూ\n\nచూ\n\nచూ\n\nచూ\n\nచూ\n\nచూ\n\nచూ\n\nచూ\n\nచూ\n\nచూ\n\nచూ\n\nచూ\n\nచూ\n\nచూ\n\nచూ\n\nచూ\n\nచూ\n\nచూ\n\nచూ\n\nచూ\n\nచూ\n\nచూ\n\nచూ\n\nచూ\n\nచూ\n\nచూ\n\nచూ\n\nచూ\n\nచూ\n\nచూ\n\nచూ\n\nచూ\n\nచూ\n\nచూ\n\nచూ\n\nచూ\n\nచూ\n\nచూ\n\nచూ\n\nచూ\n\nచూ\n\nచూ\n\nచూ\n\nచూ\n\nచూ\n\nచూ\n\nచూ\n\nచూ\n\nచూ\n\nచూ\n\nచూ\n\nచూ\n\nచూ\n\nచూ\n\nచూ\n\nచూ\n\nచూ\n\nచూ\n\nచూ\n\nచూ\n\nచూ\n\nచూ\n\nచూ\n\nచూ\n\nచూ\n\nచూ\n\nచూ\n\nచూ\n\nచూ\n\nచూ\n\nచూ\n\nచూ\n\nచూ\n\nచూ\n\nచూ\n\nచూ\n\nచూ\n\nచూ\n\nచూ\n\nచూ\n\nచూ\n\nచూ\n\nచూ\n\nచూ\n\nచూ\n\nచూ\n\nచూ\n\nచూ\n\nచూ\n\nచూ\n\nచూ\n\nచూ\n\n"
        },
        {
            "title": "గుండ్రకొమ్ముల అనుమానం",
            "page_start": 46,
            "author": "కొడుకుల నారాయణ",
            "pdf_page": 47,
            "content": "పూర్వం ఒకపూళ్లో ఒకదాసరి వుండేవాడు.\nఆదాసరి తలబోడి. దాసరి రోజూ ప్రాద్దున్నే\nముప్పికి బయలుదేరి పూళ్లోవీధులన్నీ తిరిగి\nఆ వచ్చినదానితో బ్రతుకుతూండేవాడు.\n\nదాసరి యిలా ముప్పికి వీధుల వెంబడి\nవెడుతుండేటప్పుడు ఒకవీధిలో గుండ్రంగా\nవంపుతిరిగిన కొమ్ములు న్న గేదె ఒకటి\nకనిపించేది. ఆ గేదెకొమ్ములని చూడగానే\nదాసరికి ఒకసందేహం కలుగుతూవుండేది.\n“ఈ గేదెకొమ్ముల మధ్యవున్న గుండ్రని\nఖాళీస్థలం పెద్దదా? లేక నా బోడి తల\nపెద్దదా?” అని. అయినామళ్లీ, “ఏది పెద్ద\nదైతే నాకేంటే” అని తనకితాను సమాధానం\nచెప్పుకుని మరోవీధికి వెళ్లిపోయేవాడు.\n\nకాని, ఆ వీధికి ముప్పికి వెళ్ళగానే\nదాసరికి ఆ గేదె కనిపించేది. మళ్ళీదాసరికి\nఆదే సందేహం కలుగుతూవుండేది,\n\nఒక రోజున దాసరి ఆ నుకున్నాడు.\n“ఏమిటి నాకీ ఆనుమానం? ఇదేదో, తేల్చు\nకుంటేగాని బాగుండేటట్లు లేదు.” ఇలా\nఆనుకుని ఆచుట్టుప్రక్కల కూడా ఎవరూ\nచూడటంలేదనే ధైర్యంతో దాసరి తన\nబోడితలని ఆ గేదె గుండ్రని కొమ్ముమధ్య\nవున్న ఖాళీస్థలంలోకి నెమ్మదిగా ఇరికిం\nచాడు. ఇంకేముంది? గేదెకాస్తాపించి\nగెత్తసాగింది. పాపం, దాసరితల కొమ్ములో\nచిక్కుకొంది.\n\nతల జైటికి లాకోక్కవాలని దాసరి ఎంతో\nప్రయత్నించాడు. కాని ఏమి లాభంలేక\nపోయింది. ఇక ఏమి చెయ్యటానికి తోచక\nదాసరి బాధతో “అమ్మోయ! బాబోయ!”\nఅని అరవటం మొదలెట్టాడు.\n\nఈ కేకలు విని ఆ చుట్టుప్రక్కలవా\nరంతా ఆక్కడికి పోగయ్యారు. దాసరి\n\nఅవస్త చూచేసరికి వాళ్లకి నవ్వు వచ్చింది.\nజాలీకలిగింది. అంతాచేరి మెల్లిగా దాసరి\nతలని కొమ్ము మధ్యనించి బైటికి తీశారు.\nబ్రతుకు జీవుడా అనుకొని దాసరి కాసే\nపటికి తెప్పరిల్లుకున్నాడు.\n\nఆప్పుడు వచ్చినవారంతా దాసరి చుట్టూ\nచేరి \"ఏమయ్యాదాసరీ! ఇలా నీతల ఈ గేదె\nకొమ్ములమధ్య కెందుకని ఇరుక్కుంది?\"\n\nఅని ఆడిగారు.\n\n\"ఆ, ఏముందిబాబు! దీనికంతా నా 'గుండ్రకొమ్ముల అనుమానం' కారణం\" అని చెప్పే యింత అక్కడ ఒక్క కేణం నిలిస్తే తనకి తాటాకులు కట్టకమానరని వెనక్కితిరిగి చూడకుండా వెళ్లిపోయాడు.\n\nవచ్చినవారంతా దాసరి తెలివి తక్కువకి\nకడుపు చెక్కలయ్యేటట్లు నవ్వి ఎవరిళ్లకు\nవాళ్లు చేరుకున్నారు.\n\nఆప్పట్నించి, అనవసరమైన విషయాల్లో\nజోక్యం కలిగించుకొని అవస్థలు పడేవాళ్లని\nచూస్తే ఆ వూళ్లో వాళ్ళకి దాసరిసంగతి గుర్తు.\nకొచ్చి, \"ఎందుకయ్యా నీకి గుండ్రకొమ్ముల\nఅనుమానం?\" అంటుండేవారు.\n\nమీరూ అలా అనవసరమైన పనుల్లో\nజోక్యం కల్గించుకుంటే మిమ్మల్ని అలాగే\nఅంటారు. కనక మీరు అనవసరమైన\nపనుల్లో జోక్యం కల్గించుకోకుండా ఉంటే\nదాసరి లాగా అవస్తాపడరు, ఒకరు\nమిమ్మల్ని ఏమీ అననూ అనరు.\n\nపొడుపు పద్యములు\n\n1\n\nకడుపులోని నాల్క-కదలి చెప్పుచునుండు\nదేవుడుండు చోటు - తెల్లముగను\nవిప్పి చెప్పు వెదకి - విజ్ఞానమంతయు?\n\nపందెమిత్తు వేయు . చందమామ!\n\n(నంపాదన : చిల్ల వెంకటనరసింహములు, కడప)\n\n2\n\nనీట ముంచిన, తనయందు నీఁ పోయ\nరూపమొకటియె చివిచూడ రుచియు వేరు\nవడతి యిచ్చును, మరియును పత్రమొసగు\nచెప్పు? చూతు నేనెవరినో చందమామ!\n\n(నంపాదన : చాపలి లీలాపతి, చెరుకుపల్లి)\n\n(జవాబులు 45-వ పేజీలో చూడండి)\n\nపజిలుకు జవాబు\n\nపక్క పేజీలోని చిక్కుబొమ్మలకి జవాబు\n3, 6, నెంబర్లు గల బొమ్మలు రెండు ఒక రకం\n\n‘చందశమామ’కు\nరచనలు పంపేవారుతా అది\nముఖ్యంగా గమనించాలి\n\n★\n\n‘చందమామకు’ రచనలు పంపదలచిన వారు ఆకముందు మూడు కాన్ల పోస్టుబిళ్ళ ఆంటించి పంపనక్కర్లెదు. మీరు పంపిన రచన మాకు నచ్చి, మేము ప్రచురింప దలచుకుంటే, ఆ సంగతి రచన మాకు చేరినతర్వాత 15 రోజులలోపల మీకు తెలియజేస్తాము. అలా 15 రోజుల లోపల మావద్దనుంచి మీకు వివిధమైన జవాబూ రాకపొతే మీరు పంపిన రచన ఏదో ఒక కారణంచెత మాకు నచ్చలేదని, మేము ఆంగీకరించలేవనీ మీరు తెలుసుకోవలసి వుంటుంది. ఆంగీకరింపబడని రచనలు వివిధంగానూ త్రిప్పిపంపలేము. కనక, మీరే మీ రచనకు రెండు కాపీలు వ్రాసు కుని ఒక కాపీ మాకుపంపి రెండో కాపీ మీ వద్ద ఉంచుకోటం మంచిది.\n\nపై విషయాలు చందమామ రచయిత లందరూ ఆ క ముందు ముఖ్యంగా గుర్తుంచుకో పలసిందిగా కోరుతున్నాము.\n\n— సంచాలకడు.\n\nఅబ్బాయిలూ, అమ్మాయిలూ!\n\nపైనపున్న ఆరు బొమ్మలూ ఒకేలా వున్నట్టు కనిపిస్తున్నయ్యికదూ? కాని అలా లేవు. అరింటిలో నాలుగు ఒకరకం, రెండు ఒకరకం. అది ఏవై కనుక్కోండి. మీరు కనుక్కోలేకపోతే జవాబుకు ముందుపేజీలో చూడండి.\n\nఆగస్టు 19 నుండి ఆంధ్రదేశంలో ప్రదర్శింపబడుతోంది\n\nమూడరవుధయెలుగువారి\n19 ఆగస్టున\n1000\n\nతిరపెద\nఆఫ్ఘర్యణంతామణః\n\nZACH\nSCREEN ARTS\n\nఆంధ్రుల అభ్యున్నతశార “వరలక్ష్మి” మొదలగువారు\nనటించిన అపూర్వమైన నృత్యములుగల చిత్రం.\n\nవిడుదల కేంద్రాలు:\n\nవిజయవాద — సరస్వతి, లీలామహల్\n\nతెనాలి — రత్నా\n\nవిశాఖపట్టణం — మినర్వా\n\nఏలూరు — పాండురంగ\n\nకాకినాడ — మినర్వా.\n\nకర్నూలు — దాంద్\n\nడిస్ట్రేబ్యూటర్సు :\n\nచెమియా టాకీ డిస్ట్రేబ్యూటర్సు :: విజయవాద, & గుంతకల్లు\n\n# 1000 శిరశేద అపూర్వ చింతామణి\n\nమాడరన్ థియేటర్సు వారి తమిళచిత్రం కథ\n\nవిద్యావంతరు. ప్రాజ్ఞారు. కామవిపాని అయిన ఒకవ్యక్తి అప్షమనిది పొందటానికి పూజ చేస్తారు. అదిత్యవురం రాజకుమార్తె చింతామణిద్వారా వెయ్యమంది తలం తనకి ఐలి యిప్పించినట్లయితే ఆ కోర్కె ఫరిస్తుందని ఒక టూతం వరకుతుంది. సన్యాని వేషంతో ఆ వ్యక్తి ఆడిత్యవురం వస్తారు.\n\nతెలివిగలది, అందగ తైఆయిన చింతామణి తనకుతగిన గుడవుకోసం వెడికిస్తుపుంటుంది. ఆ సమయంలో యీ కవటసన్యాని చింతామణికి గుడవుపుతారు. చింతామణి మేనమామ వురండిరన్ చింతామణిని వివాహమాదాలి కూతూహలపడతారు. చింతామణి తండ్రి అందుకు అంగీకరిస్తారు. విద్యావంతుడు, ప్రతిధాకాలి, రూపవంతుడు అయిన రాజకుమార్ణు వివాహం చేసుకోవాలంటే తిను వేసే మాడుప్రశ్నలకి నడిసైనికి సమాధానం చెప్పినవానినే వివాహ మారుకాననీ చెప్పలేనివారి తలం ఐలియిప్యాలని ప్రజల్జపూనమని గుడవైన కవటసన్యాని తన శివ్యురాలిని ఆదేశిస్తారు. ఈ కవటసన్యాని కవటసనాటకానికి గురై ప్రశ్నలకు జవాబులు చెప్పలేక తొమ్మిదివందల తొంపై తొమ్మిదిమంది రాజకుమారులు ఐలి అవుతారు.\n\nతెలంగాయిని యువరాజా మెయ్యేళహన్ కి తన ఆరుగురుపోదరులు చింతామణి ప్రశ్నలకు జవాబులు చెప్పలేక ఐలి అయినారన్న విషయం తెలిచి చింతామణిపైన చగతీర్చుకుంటానది ప్రతిజ్ఞచేస్తారు. మెయ్యేళహన్ తన స్నేహితుడు కాళిని వెంటబెట్టుకుని అదిత్యవురం చేరు కుంటారు. చింతామణి ఉద్యానవనలో తోటమారీలుగా వారిద్దరు ప్రపేక్షిస్తారు.\n\nఅవంతి రాజకుమార్తె శంకరమం తల్లి దండ్రులను విడిచి చింతామణితోనే కాలం గదు పుతూ పుంటుంది. మెయ్యేళహన్ శంకరమం మధ్య ప్రేమందం ఏర్పడుతుంది. చింతామణి మాడు ప్రశ్నల ఏమిటో వాటికి జవాబులేమిటో కనుక్కుని చెప్పరుంటారు శంకరమాన్ని తోటమాలి వేషంలో నున్న మెయ్యేళహన్. మధిలవడనపురం, సంపంగిపురం, నడిశీలపురం ఆనే మాడునగరాల్లోను ఆ మాడుప్రశ్నలకు జవాబులు తెలిస్తాయి శంకరమంచెప్పుతుంది.\n\nతన స్నేహితుడు కాళితోనహా మెయ్యేళహన్ మదివడనపురం చేరుకుంటారు. మదివడనపురం రాజాకి ఒక సన్యాశిచేసిన అవదారం గురించిన కథ విని చింతామణి గుడవు అయిన కవటసన్యానే ఆతడవి తెలుసుకుని. చింతామణి మొదటిప్రశ్నకు వివాటు చెప్పమని మదివడనపురం రాజా అయిన నక్షతీఁదిని కోర్తారు మెయ్యేళహన్. మిగత రెండ ప్రశ్నలకు జవాబు తెలుసు కునేందుకు, నక్షతీఁదినితోనహా మెయ్యేళహన్ సంపంగిపురం చేరుకుంటారు. చింతామణి గురువు సంపంగిపురం రాజాకు కూడా అవిదారంచేసిన విషయం తెలుసుకుని సంపంగిపురం రాజాతో నడిశీలపురంచేరుకుంటారు. చింతామణి గురువు నడిశీలపురం రాజాకుకూడా గ్రోహం చేకాడనేవిషయం తెలుసుకుని యీ ముగ్గురు రాజాలు. మెయ్యేళహన్ ఆ కవటసన్యానిపైన పగతీర్యుకోటానికి అదిత్యవురంకి వెళతారు.\n\nగుహోవల సన్యాని, గుహైట చింతామణి వుండగా వీరందరు వెళ్ళి చింతామణిని ప్రశ్నలడగమని జవాబులు చెప్పాతారు. కవటసన్యాని కవటసనాటకం వెల్లడవుకుంది. చింతామణి ప్రశ్నలకు జవాబులు చెప్పలేక సన్యాని కవటస నాటకానికి గురియై ఐలికాబడ్డ 999 రాజకుమారులకు పునర్జామ్మ యిప్యమని నడిశీలపురంరాజా సన్యానిని అణ్ణాపస్తారు. 999 మందికి ప్రాణంతోస్తారు ఏపటనన్యాని. వెంటనే సన్యానిని తుడముద్దిస్తారు. చింతామణి ఐలిగొన్న వెయ్యోజీవం కవటసన్యాని. శంకరమాన్ని మెయ్యేళహన్ వివాహమాడుతారు. పునర్జమ్మ కలిగిన చింతామణి మేనమామ పురందిరన్ చింతామణిని వివాహమాడుతారు.\n\nమాడు పట్టణల్లోను సన్యానికాదించిన దురంతాలకథలు చిత్రంలో సమగ్రంగా చూపించడుతిని.\n\nనాజూకుకు .. నాణ్యానికి .. మన్నికకు .. ప్రసిద్ధిగాంచిన పింగాణీ వస్తుపులు.\n\nఇండియా సిరొమిక్స్ లిమిటెడ్\n\nనెల్లూరు : కాళుహస్తి : మద్రాసు\n\nఈస్ట్ & వెస్ట్ ఇస్ట్ కొంపెనీ, లిమిటెడ్, బొంబాయి.\n\n[ 1913లో స్థానికము ]\n\nప్రధానకార్యాలయం: 'ఈస్ట్ అండ్ వెస్ట్ బిల్డింగ్', పోర్టు, బొంబాయి.\n\n34 సంవత్సరాలుగా దేశపేవచేస్తూ శాతియోన్నతి పెంపొందిస్తూ ఉన్న ప్రముఖ భారతీయ లీమా సంస్థ. ఆర్థికంగా మన్డిరమై. పాంపీదార్ల తోమా, ఏజంట్లతోమా వ్యవహరించుటలో సంస్కారానికి వేరెన్నికగన్న సంస్థ.\n\n1944లో జరిపిన ఆదనపు వ్యాపారం కోటి రూపాయలు మించింది. చురుకైనటువంటిన్నీ. పలుకుబడి కలిగినటువంటిన్నీ వ్యస్తులు ఏజన్పీలకొంటూ దరఫాస్తులు పెట్టుకోవచ్చును.\n\nవివరాలకు:\n\nశ్రీ జె. యస్. రెడ్డి, ద్రాంచి చెక్రటరీ.\n\n377, ఎన్పట్లనేడ్, మద్రాసు.\n\nశ్రీ వి. ఎ. నాగరెడ్డి, చీన ఏజంటు.\n\nరాయలనీమ ఏరియా, విక్టోరియాపేట, ఆదోని.\n\nశ్రీ యస్. మల్లికార్డునరావు, ఆర్లనైజింగ్ సెక్రటరీ, బెజవాడ.\n\nసెప్టెంబరు 25-న ఆంధ్రదేశపు ముఖ్యకేంద్రాల్లో విడుదల\n\nజుసిటర్\n\nఅభిమాన్య\n\n(తెమిళం)\n\nశరత్ బాబు రచనలు\n\n<table><tr><td>వాగ్డత్త</td><td>[నవం]</td><td>1</td><td>12</td></tr><tr><td>మహద</td><td>..</td><td>1</td><td>8</td></tr><tr><td>దేవదామ</td><td>..</td><td>1</td><td>8</td></tr><tr><td>వర్తియాం</td><td>..</td><td>1</td><td>8</td></tr><tr><td>వపవిరాన్</td><td>..</td><td>1</td><td>0</td></tr><tr><td>చంద్రనార్</td><td>..</td><td>1</td><td>0</td></tr><tr><td>వరిణీక</td><td>..</td><td>0</td><td>12</td></tr><tr><td>ఐదరీదీ</td><td>..</td><td>0</td><td>12</td></tr><tr><td>పతిప్రత</td><td>..</td><td>0</td><td>12</td></tr><tr><td>హేమాంగిని</td><td>..</td><td>0</td><td>12</td></tr><tr><td>విష్కృతి</td><td>..</td><td>0</td><td>12</td></tr><tr><td>మావాడ</td><td>..</td><td>0</td><td>12</td></tr><tr><td>కాశీనార్</td><td>..</td><td>0</td><td>12</td></tr><tr><td>మహేశుడు</td><td>[కశణ]</td><td>0</td><td>12</td></tr><tr><td>నారిర్మాల్య</td><td>[వ్యావహారి]</td><td>0</td><td>12</td></tr></table>\n\nడిటెక్టివు నవలలు\n\n<table><tr><td>కడవటిమాట</td><td>..</td><td>0</td><td>12</td></tr><tr><td>మాయమైన మణిహారం</td><td>..</td><td>0</td><td>12</td></tr><tr><td>తప్పిటోయిన పెళ్లికూతుడు</td><td>..</td><td>0</td><td>12</td></tr><tr><td>తగినళా స్త్రీ</td><td>..</td><td>0</td><td>12</td></tr><tr><td>పాఠిటోయిన యుద్ధమైని</td><td>..</td><td>0</td><td>12</td></tr><tr><td>దివాళా ఎస్టేట్</td><td>..</td><td>0</td><td>12</td></tr><tr><td>అంతులేని ఆశ</td><td>..</td><td>0</td><td>12</td></tr></table>\n\nచక్రపాణి అనువాదాలు\n\n<table><tr><td>శారీదేవి [మైత్రా] అనువాదం కశణ</td><td>1</td><td>8</td></tr><tr><td>వరాజయం</td><td>..</td><td>0</td><td>12</td></tr><tr><td>ఉదరవిమిత్తం [నాటకం]</td><td>1</td><td>0</td></tr><tr><td>వల్లభపురం చిట్టడపిలో [రాహువారధి] [నాటికం]</td><td>0</td><td>12</td></tr><tr><td>హనుమంతుని న్యస్పం [పరళురాం]</td><td>0</td><td>12</td></tr><tr><td>మెట్టవేదాంతం [వచష్టాల్]</td><td>1</td><td>0</td></tr><tr><td>లెంగారీకశణ</td><td>[మనోవైజ్ఞానిక కశణ]</td><td>0</td><td>12</td></tr><tr><td>ప్రగల్పప్రేక్షమా [అత్యుత్తమ కశణ]</td><td>0</td><td>12</td></tr><tr><td>పాంచజన్యం [రాజసీయ కశణ]</td><td>0</td><td>12</td></tr><tr><td>డిలెక్టివు [నాటికం]</td><td>0</td><td>12</td></tr><tr><td>అందికర్ణ</td><td>[పరళురాం కశణ]</td><td>1</td><td>0</td></tr></table>\n\nకుటుంబరావు రచనలు\n\n<table><tr><td>విలవసీడు [అత్యుత్తమ కశణ]</td><td>1</td><td>8</td></tr><tr><td>మొండివాడు</td><td>..</td><td>1</td><td>0</td></tr><tr><td>కాంపైరవుడు</td><td>..</td><td>0</td><td>12</td></tr><tr><td>వరప్రసాదం</td><td>..</td><td>0</td><td>12</td></tr><tr><td>కవిరాట్టు [గల్ఫికలు]</td><td>0</td><td>12</td></tr><tr><td>కులంలేని మనిషి [వసం]</td><td>0</td><td>12</td></tr><tr><td>అరుణోదయం</td><td>..</td><td>1</td><td>0</td></tr><tr><td>మారువేళ్లు</td><td>..</td><td>0</td><td>12</td></tr><tr><td>వీశేం కావాలి :</td><td>..</td><td>0</td><td>12</td></tr><tr><td>ప్రణయరోగుణ [నాటికం]</td><td>1</td><td>0</td></tr></table>\n\nఅన్ని హిగిన్ బాధమ్ము స్టాల్సులోనూ దొరుకుతది. లేదా మాకు వ్రాయంతి.\n6-0-0 వుస్త్రకాలు తెప్పంచిన పోస్టు ఖిర్చులు మేమే భరించెదము.\n\nయువ బుక్ డిపో\nపోస్టుబాక్సు నెంబరు: 1686, మద్రాను.\n\n3 కోట్ల ఆంధ్రులకు 3 ఉత్తమ పత్రికలు\nనేడే చందాదారులుకండి!\n\nచంద్రమామ\nపిల్లలకు\n\nసాలుచందా 3-0-0\n\nరెండేండ్లకు 5-0-0\n\nపాలుచందా 5-0-0\n\nరెండేండ్లకు 9-0-0\n\nయువ విద్యార్ధులకు\n\nఆంధ్రజ్ఞుతి\nపెద్దలకు\n\nసాలుచందా 5-8-0\n\nరెండేండ్లకు 10-0-0\n\nఆఫీను\n\nపోస్టు బాక్సు నెం. 1686 :: మద్దాసు-1\n\nత్వరలో ఆంధ్రదేశంలో ఎడుదల!\n\nరాగిణీ వారి\nభక్త\nజనా\nతమ శం\n\nతారాగణం : తాంతకుమార్తి, నాగయ్య హోన్నప్ప భాగవతార్, సారంగపాణి మొదలై నవారు.\n\nడైరెక్టర్.. పి.పుల్లయ్య.ఏ\n\nవిజయవాడ - నరస్వతి విక్చర్ పాలెన్\n\nగుంటూరు - నరస్వతీ టాకీన్\n\nవిజయవగరం - శ్రీ కృష్ణా సివిమా\n\nబందరు - మినర్వా టాకీన్\n\nరాజమహేంద్రవరం - జయా టాకీన్\n\nబిల్లారి - గ్రాండ్ థియేటర్\n\nఇంకా తదితర కేంద్రాల్లో విడుదలకి ఎదురుచూడండి.\n\nఆంధ్ర, దత్త మండలాలకి డిస్ట్రిబ్యూటర్లు :\n\nవాహినీ విక్చర్స్ లిమిటెడ్:: మధ్రాసు - విజయవాడ - తాడిపతి"
        }
    ]
}